[{"l_1": 34, "l_2": 34, "h": 12, "f_c": 5000, "c_1": 24, "c_2": 24, "bay": {"l_1": "exterior", "l_2": "interior"}, "l_ratio": 1.0, "f_y": 60000, "w_c": 150, "nu": 0.2, "loading": {"sdl": 0, "ll_design": 80, "ll_vib": 11}, "reinforcement": {"type": "estimated"}, "phi": 0.9, "rho": {"l_1": {"column": {"p": 0.00335, "n1": 0.00279, "n2": 0.00564}, "middle": {"p": 0.0025, "n1": 0.0025, "n2": 0.0025}}, "l_2": {"column": {"p": 0.0025, "n1": 0.00523, "n2": 0.00523}, "middle": {"p": 0.0025, "n1": 0.0025, "n2": 0.0025}}}, "E_c": 5144190.898479565, "lambda_cw": 1.0, "n": 5.637426870875134, "f_r": 318.1980515339464, "strips": {"l_1": {"column": 17.0, "middle": 17.0}, "l_2": {"column": 17.0, "middle": 17.0}}, "mass": 5779.999999999999, "weight": 186.116, "rho_max": 0.021250000000000005, "bending_moments": {"l_1": {"service": {"column": {"n1": {"dl": 169.7, "ll": 90.5}, "n2": {"dl": 342.7, "ll": 182.8}, "p": {"dl": 203.7, "ll": 108.6}}, "middle": {"n1": {"dl": 0.0, "ll": 0.0}, "n2": {"dl": 114.2, "ll": 60.9}, "p": {"dl": 135.8, "ll": 72.4}}}, "factored": {"column": {"n1": 348.4, "n2": 703.7, "p": 418.2}, "middle": {"n1": 0.0, "n2": 234.5, "p": 278.8}}}, "l_2": {"service": {"column": {"n1": {"dl": 318.2, "ll": 169.7}, "n2": {"dl": 318.2, "ll": 169.7}, "p": {"dl": 137.1, "ll": 73.1}}, "middle": {"n1": {"dl": 106.1, "ll": 56.6}, "n2": {"dl": 106.1, "ll": 56.6}, "p": {"dl": 91.4, "ll": 48.7}}}, "factored": {"column": {"n1": 653.4, "n2": 653.4, "p": 281.5}, "middle": {"n1": 217.9, "n2": 217.9, "p": 187.6}}}}, "I_e": 15512.599999999999, "I_g": 58752.0, "k_1": 0.26403526688453155, "f_i": 3.4320642091524487, "vib": {"beta": 0.03, "very_slow": {"V_13": 3382.0, "crit": "pass"}, "slow": {"V_13": 12010.0, "crit": "fail"}, "moderate": {"V_13": 12430.0, "crit": "fail"}, "fast": {"V_13": 12863.0, "crit": "fail"}}}, {"l_1": 34, "l_2": 34, "h": 12, "f_c": 5000, "c_1": 26, "c_2": 26, "bay": {"l_1": "exterior", "l_2": "interior"}, "l_ratio": 1.0, "f_y": 60000, "w_c": 150, "nu": 0.2, "loading": {"sdl": 0, "ll_design": 80, "ll_vib": 11}, "reinforcement": {"type": "estimated"}, "phi": 0.9, "rho": {"l_1": {"column": {"p": 0.00332, "n1": 0.00276, "n2": 0.00558}, "middle": {"p": 0.0025, "n1": 0.0025, "n2": 0.0025}}, "l_2": {"column": {"p": 0.0025, "n1": 0.00518, "n2": 0.00518}, "middle": {"p": 0.0025, "n1": 0.0025, "n2": 0.0025}}}, "E_c": 5144190.898479565, "lambda_cw": 1.0, "n": 5.637426870875134, "f_r": 318.1980515339464, "strips": {"l_1": {"column": 17.0, "middle": 17.0}, "l_2": {"column": 17.0, "middle": 17.0}}, "mass": 5779.999999999999, "weight": 186.116, "rho_max": 0.021250000000000005, "bending_moments": {"l_1": {"service": {"column": {"n1": {"dl": 168.0, "ll": 89.6}, "n2": {"dl": 339.2, "ll": 180.9}, "p": {"dl": 201.6, "ll": 107.5}}, "middle": {"n1": {"dl": 0.0, "ll": 0.0}, "n2": {"dl": 113.1, "ll": 60.3}, "p": {"dl": 134.4, "ll": 71.7}}}, "factored": {"column": {"n1": 345.0, "n2": 696.5, "p": 413.9}, "middle": {"n1": 0.0, "n2": 232.2, "p": 276.0}}}, "l_2": {"service": {"column": {"n1": {"dl": 314.9, "ll": 168.0}, "n2": {"dl": 314.9, "ll": 168.0}, "p": {"dl": 135.7, "ll": 72.4}}, "middle": {"n1": {"dl": 105.0, "ll": 56.0}, "n2": {"dl": 105.0, "ll": 56.0}, "p": {"dl": 90.4, "ll": 48.2}}}, "factored": {"column": {"n1": 646.7, "n2": 646.7, "p": 278.7}, "middle": {"n1": 215.6, "n2": 215.6, "p": 185.6}}}}, "I_e": 16268.549999999997, "I_g": 58752.0, "k_1": 0.27690206290849667, "f_i": 3.8846618828665256, "vib": {"beta": 0.03, "very_slow": {"V_13": 2972.0, "crit": "pass"}, "slow": {"V_13": 10796.0, "crit": "fail"}, "moderate": {"V_13": 11223.0, "crit": "fail"}, "fast": {"V_13": 11667.0, "crit": "fail"}}}, {"l_1": 34, "l_2": 34, "h": 12, "f_c": 5000, "c_1": 28, "c_2": 28, "bay": {"l_1": "exterior", "l_2": "interior"}, "l_ratio": 1.0, "f_y": 60000, "w_c": 150, "nu": 0.2, "loading": {"sdl": 0, "ll_design": 80, "ll_vib": 11}, "reinforcement": {"type": "estimated"}, "phi": 0.9, "rho": {"l_1": {"column": {"p": 0.00328, "n1": 0.00274, "n2": 0.00552}, "middle": {"p": 0.0025, "n1": 0.0025, "n2": 0.0025}}, "l_2": {"column": {"p": 0.0025, "n1": 0.00513, "n2": 0.00513}, "middle": {"p": 0.0025, "n1": 0.0025, "n2": 0.0025}}}, "E_c": 5144190.898479565, "lambda_cw": 1.0, "n": 5.637426870875134, "f_r": 318.1980515339464, "strips": {"l_1": {"column": 17.0, "middle": 17.0}, "l_2": {"column": 17.0, "middle": 17.0}}, "mass": 5779.999999999999, "weight": 186.116, "rho_max": 0.021250000000000005, "bending_moments": {"l_1": {"service": {"column": {"n1": {"dl": 166.2, "ll": 88.6}, "n2": {"dl": 335.6, "ll": 179.0}, "p": {"dl": 199.5, "ll": 106.4}}, "middle": {"n1": {"dl": 0.0, "ll": 0.0}, "n2": {"dl": 111.9, "ll": 59.7}, "p": {"dl": 133.0, "ll": 70.9}}}, "factored": {"column": {"n1": 341.2, "n2": 689.1, "p": 409.6}, "middle": {"n1": 0.0, "n2": 229.8, "p": 273.0}}}, "l_2": {"service": {"column": {"n1": {"dl": 311.6, "ll": 166.2}, "n2": {"dl": 311.6, "ll": 166.2}, "p": {"dl": 134.2, "ll": 71.6}}, "middle": {"n1": {"dl": 103.9, "ll": 55.4}, "n2": {"dl": 103.9, "ll": 55.4}, "p": {"dl": 89.5, "ll": 47.7}}}, "factored": {"column": {"n1": 639.8, "n2": 639.8, "p": 275.6}, "middle": {"n1": 213.3, "n2": 213.3, "p": 183.7}}}}, "I_e": 17127.35, "I_g": 58752.0, "k_1": 0.29151943763616556, "f_i": 3.985876950974316, "vib": {"beta": 0.03, "very_slow": {"V_13": 2884.0, "crit": "pass"}, "slow": {"V_13": 10529.0, "crit": "fail"}, "moderate": {"V_13": 10958.0, "crit": "fail"}, "fast": {"V_13": 11404.0, "crit": "fail"}}}, {"l_1": 34, "l_2": 34, "h": 12, "f_c": 5000, "c_1": 30, "c_2": 30, "bay": {"l_1": "exterior", "l_2": "interior"}, "l_ratio": 1.0, "f_y": 60000, "w_c": 150, "nu": 0.2, "loading": {"sdl": 0, "ll_design": 80, "ll_vib": 11}, "reinforcement": {"type": "estimated"}, "phi": 0.9, "rho": {"l_1": {"column": {"p": 0.00325, "n1": 0.0027, "n2": 0.00546}, "middle": {"p": 0.0025, "n1": 0.0025, "n2": 0.0025}}, "l_2": {"column": {"p": 0.0025, "n1": 0.00508, "n2": 0.00508}, "middle": {"p": 0.0025, "n1": 0.0025, "n2": 0.0025}}}, "E_c": 5144190.898479565, "lambda_cw": 1.0, "n": 5.637426870875134, "f_r": 318.1980515339464, "strips": {"l_1": {"column": 17.0, "middle": 17.0}, "l_2": {"column": 17.0, "middle": 17.0}}, "mass": 5779.999999999999, "weight": 186.116, "rho_max": 0.021250000000000005, "bending_moments": {"l_1": {"service": {"column": {"n1": {"dl": 164.5, "ll": 87.7}, "n2": {"dl": 332.1, "ll": 177.1}, "p": {"dl": 197.4, "ll": 105.3}}, "middle": {"n1": {"dl": 0.0, "ll": 0.0}, "n2": {"dl": 110.7, "ll": 59.0}, "p": {"dl": 131.6, "ll": 70.2}}}, "factored": {"column": {"n1": 337.7, "n2": 681.9, "p": 405.4}, "middle": {"n1": 0.0, "n2": 227.2, "p": 270.2}}}, "l_2": {"service": {"column": {"n1": {"dl": 308.4, "ll": 164.5}, "n2": {"dl": 308.4, "ll": 164.5}, "p": {"dl": 132.8, "ll": 70.8}}, "middle": {"n1": {"dl": 102.8, "ll": 54.8}, "n2": {"dl": 102.8, "ll": 54.8}, "p": {"dl": 88.6, "ll": 47.2}}}, "factored": {"column": {"n1": 633.3, "n2": 633.3, "p": 272.6}, "middle": {"n1": 211.0, "n2": 211.0, "p": 181.8}}}}, "I_e": 18172.15, "I_g": 58752.0, "k_1": 0.30930266203703705, "f_i": 4.1056503194747345, "vib": {"beta": 0.03, "very_slow": {"V_13": 2794.0, "crit": "pass"}, "slow": {"V_13": 10251.0, "crit": "fail"}, "moderate": {"V_13": 10681.0, "crit": "fail"}, "fast": {"V_13": 11129.0, "crit": "fail"}}}, {"l_1": 34, "l_2": 34, "h": 12, "f_c": 5000, "c_1": 32, "c_2": 32, "bay": {"l_1": "exterior", "l_2": "interior"}, "l_ratio": 1.0, "f_y": 60000, "w_c": 150, "nu": 0.2, "loading": {"sdl": 0, "ll_design": 80, "ll_vib": 11}, "reinforcement": {"type": "estimated"}, "phi": 0.9, "rho": {"l_1": {"column": {"p": 0.00321, "n1": 0.00268, "n2": 0.0054}, "middle": {"p": 0.0025, "n1": 0.0025, "n2": 0.0025}}, "l_2": {"column": {"p": 0.0025, "n1": 0.00502, "n2": 0.00502}, "middle": {"p": 0.0025, "n1": 0.0025, "n2": 0.0025}}}, "E_c": 5144190.898479565, "lambda_cw": 1.0, "n": 5.637426870875134, "f_r": 318.1980515339464, "strips": {"l_1": {"column": 17.0, "middle": 17.0}, "l_2": {"column": 17.0, "middle": 17.0}}, "mass": 5779.999999999999, "weight": 186.116, "rho_max": 0.021250000000000005, "bending_moments": {"l_1": {"service": {"column": {"n1": {"dl": 162.7, "ll": 86.8}, "n2": {"dl": 328.6, "ll": 175.2}, "p": {"dl": 195.3, "ll": 104.1}}, "middle": {"n1": {"dl": 0.0, "ll": 0.0}, "n2": {"dl": 109.5, "ll": 58.4}, "p": {"dl": 130.2, "ll": 69.4}}}, "factored": {"column": {"n1": 334.1, "n2": 674.6, "p": 400.9}, "middle": {"n1": 0.0, "n2": 224.8, "p": 267.3}}}, "l_2": {"service": {"column": {"n1": {"dl": 305.1, "ll": 162.7}, "n2": {"dl": 305.1, "ll": 162.7}, "p": {"dl": 131.4, "ll": 70.1}}, "middle": {"n1": {"dl": 101.7, "ll": 54.2}, "n2": {"dl": 101.7, "ll": 54.2}, "p": {"dl": 87.6, "ll": 46.7}}}, "factored": {"column": {"n1": 626.4, "n2": 626.4, "p": 269.8}, "middle": {"n1": 208.8, "n2": 208.8, "p": 179.8}}}}, "I_e": 19581.1, "I_g": 58752.0, "k_1": 0.3332839733115468, "f_i": 4.2618419870609054, "vib": {"beta": 0.03, "very_slow": {"V_13": 2688.0, "crit": "pass"}, "slow": {"V_13": 9919.0, "crit": "fail"}, "moderate": {"V_13": 10350.0, "crit": "fail"}, "fast": {"V_13": 10801.0, "crit": "fail"}}}, {"l_1": 34, "l_2": 34, "h": 13, "f_c": 5000, "c_1": 24, "c_2": 24, "bay": {"l_1": "exterior", "l_2": "interior"}, "l_ratio": 1.0, "f_y": 60000, "w_c": 150, "nu": 0.2, "loading": {"sdl": 0, "ll_design": 80, "ll_vib": 11}, "reinforcement": {"type": "estimated"}, "phi": 0.9, "rho": {"l_1": {"column": {"p": 0.00294, "n1": 0.0025, "n2": 0.00495}, "middle": {"p": 0.0025, "n1": 0.0025, "n2": 0.0025}}, "l_2": {"column": {"p": 0.0025, "n1": 0.0046, "n2": 0.0046}, "middle": {"p": 0.0025, "n1": 0.0025, "n2": 0.0025}}}, "E_c": 5144190.898479565, "lambda_cw": 1.0, "n": 5.637426870875134, "f_r": 318.1980515339464, "strips": {"l_1": {"column": 17.0, "middle": 17.0}, "l_2": {"column": 17.0, "middle": 17.0}}, "mass": 6228.757763975154, "weight": 200.566, "rho_max": 0.021250000000000005, "bending_moments": {"l_1": {"service": {"column": {"n1": {"dl": 183.9, "ll": 90.5}, "n2": {"dl": 371.3, "ll": 182.8}, "p": {"dl": 220.6, "ll": 108.6}}, "middle": {"n1": {"dl": 0.0, "ll": 0.0}, "n2": {"dl": 123.8, "ll": 60.9}, "p": {"dl": 147.1, "ll": 72.4}}}, "factored": {"column": {"n1": 365.5, "n2": 738.0, "p": 438.5}, "middle": {"n1": 0.0, "n2": 246.0, "p": 292.4}}}, "l_2": {"service": {"column": {"n1": {"dl": 344.8, "ll": 169.7}, "n2": {"dl": 344.8, "ll": 169.7}, "p": {"dl": 148.5, "ll": 73.1}}, "middle": {"n1": {"dl": 114.9, "ll": 56.6}, "n2": {"dl": 114.9, "ll": 56.6}, "p": {"dl": 99.0, "ll": 48.7}}}, "factored": {"column": {"n1": 685.3, "n2": 685.3, "p": 295.2}, "middle": {"n1": 228.4, "n2": 228.4, "p": 196.7}}}}, "I_e": 35609.0, "I_g": 74698.0, "k_1": 0.476706203646684, "f_i": 5.00905954644637, "vib": {"beta": 0.03, "very_slow": {"V_13": 2083.0, "crit": "pass"}, "slow": {"V_13": 7872.0, "crit": "fail"}, "moderate": {"V_13": 8276.0, "crit": "fail"}, "fast": {"V_13": 8702.0, "crit": "fail"}}}, {"l_1": 34, "l_2": 34, "h": 13, "f_c": 5000, "c_1": 26, "c_2": 26, "bay": {"l_1": "exterior", "l_2": "interior"}, "l_ratio": 1.0, "f_y": 60000, "w_c": 150, "nu": 0.2, "loading": {"sdl": 0, "ll_design": 80, "ll_vib": 11}, "reinforcement": {"type": "estimated"}, "phi": 0.9, "rho": {"l_1": {"column": {"p": 0.00291, "n1": 0.0025, "n2": 0.0049}, "middle": {"p": 0.0025, "n1": 0.0025, "n2": 0.0025}}, "l_2": {"column": {"p": 0.0025, "n1": 0.00455, "n2": 0.00455}, "middle": {"p": 0.0025, "n1": 0.0025, "n2": 0.0025}}}, "E_c": 5144190.898479565, "lambda_cw": 1.0, "n": 5.637426870875134, "f_r": 318.1980515339464, "strips": {"l_1": {"column": 17.0, "middle": 17.0}, "l_2": {"column": 17.0, "middle": 17.0}}, "mass": 6228.757763975154, "weight": 200.566, "rho_max": 0.021250000000000005, "bending_moments": {"l_1": {"service": {"column": {"n1": {"dl": 182.0, "ll": 89.6}, "n2": {"dl": 367.4, "ll": 180.9}, "p": {"dl": 218.4, "ll": 107.5}}, "middle": {"n1": {"dl": 0.0, "ll": 0.0}, "n2": {"dl": 122.5, "ll": 60.3}, "p": {"dl": 145.6, "ll": 71.7}}}, "factored": {"column": {"n1": 361.8, "n2": 730.3, "p": 434.1}, "middle": {"n1": 0.0, "n2": 243.5, "p": 289.4}}}, "l_2": {"service": {"column": {"n1": {"dl": 341.2, "ll": 168.0}, "n2": {"dl": 341.2, "ll": 168.0}, "p": {"dl": 147.0, "ll": 72.4}}, "middle": {"n1": {"dl": 113.7, "ll": 56.0}, "n2": {"dl": 113.7, "ll": 56.0}, "p": {"dl": 98.0, "ll": 48.2}}}, "factored": {"column": {"n1": 678.2, "n2": 678.2, "p": 292.2}, "middle": {"n1": 226.0, "n2": 226.0, "p": 194.7}}}}, "I_e": 35807.1, "I_g": 74698.0, "k_1": 0.47935821574874826, "f_i": 5.551707467181132, "vib": {"beta": 0.03, "very_slow": {"V_13": 1853.0, "crit": "pass"}, "slow": {"V_13": 7086.0, "crit": "fail"}, "moderate": {"V_13": 7490.0, "crit": "fail"}, "fast": {"V_13": 7918.0, "crit": "fail"}}}, {"l_1": 34, "l_2": 34, "h": 13, "f_c": 5000, "c_1": 28, "c_2": 28, "bay": {"l_1": "exterior", "l_2": "interior"}, "l_ratio": 1.0, "f_y": 60000, "w_c": 150, "nu": 0.2, "loading": {"sdl": 0, "ll_design": 80, "ll_vib": 11}, "reinforcement": {"type": "estimated"}, "phi": 0.9, "rho": {"l_1": {"column": {"p": 0.00288, "n1": 0.0025, "n2": 0.00485}, "middle": {"p": 0.0025, "n1": 0.0025, "n2": 0.0025}}, "l_2": {"column": {"p": 0.0025, "n1": 0.0045, "n2": 0.0045}, "middle": {"p": 0.0025, "n1": 0.0025, "n2": 0.0025}}}, "E_c": 5144190.898479565, "lambda_cw": 1.0, "n": 5.637426870875134, "f_r": 318.1980515339464, "strips": {"l_1": {"column": 17.0, "middle": 17.0}, "l_2": {"column": 17.0, "middle": 17.0}}, "mass": 6228.757763975154, "weight": 200.566, "rho_max": 0.021250000000000005, "bending_moments": {"l_1": {"service": {"column": {"n1": {"dl": 180.1, "ll": 88.6}, "n2": {"dl": 363.6, "ll": 179.0}, "p": {"dl": 216.1, "ll": 106.4}}, "middle": {"n1": {"dl": 0.0, "ll": 0.0}, "n2": {"dl": 121.2, "ll": 59.7}, "p": {"dl": 144.0, "ll": 70.9}}}, "factored": {"column": {"n1": 357.9, "n2": 722.7, "p": 429.6}, "middle": {"n1": 0.0, "n2": 241.0, "p": 286.2}}}, "l_2": {"service": {"column": {"n1": {"dl": 337.6, "ll": 166.2}, "n2": {"dl": 337.6, "ll": 166.2}, "p": {"dl": 145.4, "ll": 71.6}}, "middle": {"n1": {"dl": 112.5, "ll": 55.4}, "n2": {"dl": 112.5, "ll": 55.4}, "p": {"dl": 97.0, "ll": 47.7}}}, "factored": {"column": {"n1": 671.0, "n2": 671.0, "p": 289.0}, "middle": {"n1": 223.6, "n2": 223.6, "p": 192.7}}}}, "I_e": 36039.35, "I_g": 74698.0, "k_1": 0.4824674020723446, "f_i": 5.569682952906583, "vib": {"beta": 0.03, "very_slow": {"V_13": 1845.0, "crit": "pass"}, "slow": {"V_13": 7059.0, "crit": "fail"}, "moderate": {"V_13": 7464.0, "crit": "fail"}, "fast": {"V_13": 7891.0, "crit": "fail"}}}, {"l_1": 34, "l_2": 34, "h": 13, "f_c": 5000, "c_1": 30, "c_2": 30, "bay": {"l_1": "exterior", "l_2": "interior"}, "l_ratio": 1.0, "f_y": 60000, "w_c": 150, "nu": 0.2, "loading": {"sdl": 0, "ll_design": 80, "ll_vib": 11}, "reinforcement": {"type": "estimated"}, "phi": 0.9, "rho": {"l_1": {"column": {"p": 0.00285, "n1": 0.0025, "n2": 0.0048}, "middle": {"p": 0.0025, "n1": 0.0025, "n2": 0.0025}}, "l_2": {"column": {"p": 0.0025, "n1": 0.00446, "n2": 0.00446}, "middle": {"p": 0.0025, "n1": 0.0025, "n2": 0.0025}}}, "E_c": 5144190.898479565, "lambda_cw": 1.0, "n": 5.637426870875134, "f_r": 318.1980515339464, "strips": {"l_1": {"column": 17.0, "middle": 17.0}, "l_2": {"column": 17.0, "middle": 17.0}}, "mass": 6228.757763975154, "weight": 200.566, "rho_max": 0.021250000000000005, "bending_moments": {"l_1": {"service": {"column": {"n1": {"dl": 178.2, "ll": 87.7}, "n2": {"dl": 359.8, "ll": 177.1}, "p": {"dl": 213.8, "ll": 105.3}}, "middle": {"n1": {"dl": 0.0, "ll": 0.0}, "n2": {"dl": 119.9, "ll": 59.0}, "p": {"dl": 142.5, "ll": 70.2}}}, "factored": {"column": {"n1": 354.2, "n2": 715.1, "p": 425.0}, "middle": {"n1": 0.0, "n2": 238.3, "p": 283.3}}}, "l_2": {"service": {"column": {"n1": {"dl": 334.1, "ll": 164.5}, "n2": {"dl": 334.1, "ll": 164.5}, "p": {"dl": 143.9, "ll": 70.8}}, "middle": {"n1": {"dl": 111.4, "ll": 54.8}, "n2": {"dl": 111.4, "ll": 54.8}, "p": {"dl": 95.9, "ll": 47.2}}}, "factored": {"column": {"n1": 664.1, "n2": 664.1, "p": 286.0}, "middle": {"n1": 221.4, "n2": 221.4, "p": 190.6}}}}, "I_e": 36292.7, "I_g": 74698.0, "k_1": 0.48585905914482314, "f_i": 5.589225590993883, "vib": {"beta": 0.03, "very_slow": {"V_13": 1837.0, "crit": "pass"}, "slow": {"V_13": 7032.0, "crit": "fail"}, "moderate": {"V_13": 7437.0, "crit": "fail"}, "fast": {"V_13": 7864.0, "crit": "fail"}}}, {"l_1": 34, "l_2": 34, "h": 13, "f_c": 5000, "c_1": 32, "c_2": 32, "bay": {"l_1": "exterior", "l_2": "interior"}, "l_ratio": 1.0, "f_y": 60000, "w_c": 150, "nu": 0.2, "loading": {"sdl": 0, "ll_design": 80, "ll_vib": 11}, "reinforcement": {"type": "estimated"}, "phi": 0.9, "rho": {"l_1": {"column": {"p": 0.00282, "n1": 0.0025, "n2": 0.00474}, "middle": {"p": 0.0025, "n1": 0.0025, "n2": 0.0025}}, "l_2": {"column": {"p": 0.0025, "n1": 0.00441, "n2": 0.00441}, "middle": {"p": 0.0025, "n1": 0.0025, "n2": 0.0025}}}, "E_c": 5144190.898479565, "lambda_cw": 1.0, "n": 5.637426870875134, "f_r": 318.1980515339464, "strips": {"l_1": {"column": 17.0, "middle": 17.0}, "l_2": {"column": 17.0, "middle": 17.0}}, "mass": 6228.757763975154, "weight": 200.566, "rho_max": 0.021250000000000005, "bending_moments": {"l_1": {"service": {"column": {"n1": {"dl": 176.3, "ll": 86.8}, "n2": {"dl": 356.0, "ll": 175.2}, "p": {"dl": 211.5, "ll": 104.1}}, "middle": {"n1": {"dl": 0.0, "ll": 0.0}, "n2": {"dl": 118.7, "ll": 58.4}, "p": {"dl": 141.0, "ll": 69.4}}}, "factored": {"column": {"n1": 350.4, "n2": 707.5, "p": 420.4}, "middle": {"n1": 0.0, "n2": 235.9, "p": 280.2}}}, "l_2": {"service": {"column": {"n1": {"dl": 330.5, "ll": 162.7}, "n2": {"dl": 330.5, "ll": 162.7}, "p": {"dl": 142.4, "ll": 70.1}}, "middle": {"n1": {"dl": 110.2, "ll": 54.2}, "n2": {"dl": 110.2, "ll": 54.2}, "p": {"dl": 94.9, "ll": 46.7}}}, "factored": {"column": {"n1": 656.9, "n2": 656.9, "p": 283.0}, "middle": {"n1": 219.0, "n2": 219.0, "p": 188.6}}}}, "I_e": 36617.1, "I_g": 74698.0, "k_1": 0.4902018795683954, "f_i": 5.614149489175068, "vib": {"beta": 0.03, "very_slow": {"V_13": 1830.0, "crit": "pass"}, "slow": {"V_13": 7006.0, "crit": "fail"}, "moderate": {"V_13": 7410.0, "crit": "fail"}, "fast": {"V_13": 7838.0, "crit": "fail"}}}, {"l_1": 34, "l_2": 34, "h": 13, "f_c": 5000, "c_1": 24, "c_2": 24, "bay": {"l_1": "exterior", "l_2": "interior"}, "l_ratio": 1.0, "f_y": 60000, "w_c": 150, "nu": 0.2, "loading": {"sdl": 0, "ll_design": 80, "ll_vib": 11}, "reinforcement": {"type": "estimated"}, "phi": 0.9, "rho": {"l_1": {"column": {"p": 0.00294, "n1": 0.0025, "n2": 0.00495}, "middle": {"p": 0.0025, "n1": 0.0025, "n2": 0.0025}}, "l_2": {"column": {"p": 0.0025, "n1": 0.0046, "n2": 0.0046}, "middle": {"p": 0.0025, "n1": 0.0025, "n2": 0.0025}}}, "E_c": 5144190.898479565, "lambda_cw": 1.0, "n": 5.637426870875134, "f_r": 318.1980515339464, "strips": {"l_1": {"column": 17.0, "middle": 17.0}, "l_2": {"column": 17.0, "middle": 17.0}}, "mass": 6228.757763975154, "weight": 200.566, "rho_max": 0.021250000000000005, "bending_moments": {"l_1": {"service": {"column": {"n1": {"dl": 183.9, "ll": 90.5}, "n2": {"dl": 371.3, "ll": 182.8}, "p": {"dl": 220.6, "ll": 108.6}}, "middle": {"n1": {"dl": 0.0, "ll": 0.0}, "n2": {"dl": 123.8, "ll": 60.9}, "p": {"dl": 147.1, "ll": 72.4}}}, "factored": {"column": {"n1": 365.5, "n2": 738.0, "p": 438.5}, "middle": {"n1": 0.0, "n2": 246.0, "p": 292.4}}}, "l_2": {"service": {"column": {"n1": {"dl": 344.8, "ll": 169.7}, "n2": {"dl": 344.8, "ll": 169.7}, "p": {"dl": 148.5, "ll": 73.1}}, "middle": {"n1": {"dl": 114.9, "ll": 56.6}, "n2": {"dl": 114.9, "ll": 56.6}, "p": {"dl": 99.0, "ll": 48.7}}}, "factored": {"column": {"n1": 685.3, "n2": 685.3, "p": 295.2}, "middle": {"n1": 228.4, "n2": 228.4, "p": 196.7}}}}, "I_e": 35609.0, "I_g": 74698.0, "k_1": 0.476706203646684, "f_i": 5.00905954644637, "vib": {"beta": 0.03, "very_slow": {"V_13": 2083.0, "crit": "pass"}, "slow": {"V_13": 7872.0, "crit": "fail"}, "moderate": {"V_13": 8276.0, "crit": "fail"}, "fast": {"V_13": 8702.0, "crit": "fail"}}}, {"l_1": 34, "l_2": 34, "h": 13, "f_c": 5000, "c_1": 26, "c_2": 26, "bay": {"l_1": "exterior", "l_2": "interior"}, "l_ratio": 1.0, "f_y": 60000, "w_c": 150, "nu": 0.2, "loading": {"sdl": 0, "ll_design": 80, "ll_vib": 11}, "reinforcement": {"type": "estimated"}, "phi": 0.9, "rho": {"l_1": {"column": {"p": 0.00291, "n1": 0.0025, "n2": 0.0049}, "middle": {"p": 0.0025, "n1": 0.0025, "n2": 0.0025}}, "l_2": {"column": {"p": 0.0025, "n1": 0.00455, "n2": 0.00455}, "middle": {"p": 0.0025, "n1": 0.0025, "n2": 0.0025}}}, "E_c": 5144190.898479565, "lambda_cw": 1.0, "n": 5.637426870875134, "f_r": 318.1980515339464, "strips": {"l_1": {"column": 17.0, "middle": 17.0}, "l_2": {"column": 17.0, "middle": 17.0}}, "mass": 6228.757763975154, "weight": 200.566, "rho_max": 0.021250000000000005, "bending_moments": {"l_1": {"service": {"column": {"n1": {"dl": 182.0, "ll": 89.6}, "n2": {"dl": 367.4, "ll": 180.9}, "p": {"dl": 218.4, "ll": 107.5}}, "middle": {"n1": {"dl": 0.0, "ll": 0.0}, "n2": {"dl": 122.5, "ll": 60.3}, "p": {"dl": 145.6, "ll": 71.7}}}, "factored": {"column": {"n1": 361.8, "n2": 730.3, "p": 434.1}, "middle": {"n1": 0.0, "n2": 243.5, "p": 289.4}}}, "l_2": {"service": {"column": {"n1": {"dl": 341.2, "ll": 168.0}, "n2": {"dl": 341.2, "ll": 168.0}, "p": {"dl": 147.0, "ll": 72.4}}, "middle": {"n1": {"dl": 113.7, "ll": 56.0}, "n2": {"dl": 113.7, "ll": 56.0}, "p": {"dl": 98.0, "ll": 48.2}}}, "factored": {"column": {"n1": 678.2, "n2": 678.2, "p": 292.2}, "middle": {"n1": 226.0, "n2": 226.0, "p": 194.7}}}}, "I_e": 35807.1, "I_g": 74698.0, "k_1": 0.47935821574874826, "f_i": 5.551707467181132, "vib": {"beta": 0.03, "very_slow": {"V_13": 1853.0, "crit": "pass"}, "slow": {"V_13": 7086.0, "crit": "fail"}, "moderate": {"V_13": 7490.0, "crit": "fail"}, "fast": {"V_13": 7918.0, "crit": "fail"}}}, {"l_1": 34, "l_2": 34, "h": 13, "f_c": 5000, "c_1": 28, "c_2": 28, "bay": {"l_1": "exterior", "l_2": "interior"}, "l_ratio": 1.0, "f_y": 60000, "w_c": 150, "nu": 0.2, "loading": {"sdl": 0, "ll_design": 80, "ll_vib": 11}, "reinforcement": {"type": "estimated"}, "phi": 0.9, "rho": {"l_1": {"column": {"p": 0.00288, "n1": 0.0025, "n2": 0.00485}, "middle": {"p": 0.0025, "n1": 0.0025, "n2": 0.0025}}, "l_2": {"column": {"p": 0.0025, "n1": 0.0045, "n2": 0.0045}, "middle": {"p": 0.0025, "n1": 0.0025, "n2": 0.0025}}}, "E_c": 5144190.898479565, "lambda_cw": 1.0, "n": 5.637426870875134, "f_r": 318.1980515339464, "strips": {"l_1": {"column": 17.0, "middle": 17.0}, "l_2": {"column": 17.0, "middle": 17.0}}, "mass": 6228.757763975154, "weight": 200.566, "rho_max": 0.021250000000000005, "bending_moments": {"l_1": {"service": {"column": {"n1": {"dl": 180.1, "ll": 88.6}, "n2": {"dl": 363.6, "ll": 179.0}, "p": {"dl": 216.1, "ll": 106.4}}, "middle": {"n1": {"dl": 0.0, "ll": 0.0}, "n2": {"dl": 121.2, "ll": 59.7}, "p": {"dl": 144.0, "ll": 70.9}}}, "factored": {"column": {"n1": 357.9, "n2": 722.7, "p": 429.6}, "middle": {"n1": 0.0, "n2": 241.0, "p": 286.2}}}, "l_2": {"service": {"column": {"n1": {"dl": 337.6, "ll": 166.2}, "n2": {"dl": 337.6, "ll": 166.2}, "p": {"dl": 145.4, "ll": 71.6}}, "middle": {"n1": {"dl": 112.5, "ll": 55.4}, "n2": {"dl": 112.5, "ll": 55.4}, "p": {"dl": 97.0, "ll": 47.7}}}, "factored": {"column": {"n1": 671.0, "n2": 671.0, "p": 289.0}, "middle": {"n1": 223.6, "n2": 223.6, "p": 192.7}}}}, "I_e": 36039.35, "I_g": 74698.0, "k_1": 0.4824674020723446, "f_i": 5.569682952906583, "vib": {"beta": 0.03, "very_slow": {"V_13": 1845.0, "crit": "pass"}, "slow": {"V_13": 7059.0, "crit": "fail"}, "moderate": {"V_13": 7464.0, "crit": "fail"}, "fast": {"V_13": 7891.0, "crit": "fail"}}}, {"l_1": 34, "l_2": 34, "h": 14, "f_c": 5000, "c_1": 30, "c_2": 30, "bay": {"l_1": "exterior", "l_2": "interior"}, "l_ratio": 1.0, "f_y": 60000, "w_c": 150, "nu": 0.2, "loading": {"sdl": 0, "ll_design": 80, "ll_vib": 11}, "reinforcement": {"type": "estimated"}, "phi": 0.9, "rho": {"l_1": {"column": {"p": 0.00253, "n1": 0.0025, "n2": 0.00426}, "middle": {"p": 0.0025, "n1": 0.0025, "n2": 0.0025}}, "l_2": {"column": {"p": 0.0025, "n1": 0.00396, "n2": 0.00396}, "middle": {"p": 0.0025, "n1": 0.0025, "n2": 0.0025}}}, "E_c": 5144190.898479565, "lambda_cw": 1.0, "n": 5.637426870875134, "f_r": 318.1980515339464, "strips": {"l_1": {"column": 17.0, "middle": 17.0}, "l_2": {"column": 17.0, "middle": 17.0}}, "mass": 6677.51552795031, "weight": 215.016, "rho_max": 0.021250000000000005, "bending_moments": {"l_1": {"service": {"column": {"n1": {"dl": 191.9, "ll": 87.7}, "n2": {"dl": 387.4, "ll": 177.1}, "p": {"dl": 230.3, "ll": 105.3}}, "middle": {"n1": {"dl": 0.0, "ll": 0.0}, "n2": {"dl": 129.1, "ll": 59.0}, "p": {"dl": 153.5, "ll": 70.2}}}, "factored": {"column": {"n1": 370.6, "n2": 748.2, "p": 444.8}, "middle": {"n1": 0.0, "n2": 249.3, "p": 296.5}}}, "l_2": {"service": {"column": {"n1": {"dl": 359.8, "ll": 164.5}, "n2": {"dl": 359.8, "ll": 164.5}, "p": {"dl": 155.0, "ll": 70.8}}, "middle": {"n1": {"dl": 119.9, "ll": 54.8}, "n2": {"dl": 119.9, "ll": 54.8}, "p": {"dl": 103.3, "ll": 47.2}}}, "factored": {"column": {"n1": 695.0, "n2": 695.0, "p": 299.3}, "middle": {"n1": 231.6, "n2": 231.6, "p": 199.5}}}}, "I_e": 53516.3, "I_g": 93296.0, "k_1": 0.5736183759217973, "f_i": 6.5550846854048, "vib": {"beta": 0.03, "very_slow": {"V_13": 1417.0, "crit": "pass"}, "slow": {"V_13": 4869.0, "crit": "pass"}, "moderate": {"V_13": 5870.0, "crit": "pass"}, "fast": {"V_13": 6268.0, "crit": "fail"}}}, {"l_1": 34, "l_2": 34, "h": 14, "f_c": 5000, "c_1": 32, "c_2": 32, "bay": {"l_1": "exterior", "l_2": "interior"}, "l_ratio": 1.0, "f_y": 60000, "w_c": 150, "nu": 0.2, "loading": {"sdl": 0, "ll_design": 80, "ll_vib": 11}, "reinforcement": {"type": "estimated"}, "phi": 0.9, "rho": {"l_1": {"column": {"p": 0.00251, "n1": 0.0025, "n2": 0.00422}, "middle": {"p": 0.0025, "n1": 0.0025, "n2": 0.0025}}, "l_2": {"column": {"p": 0.0025, "n1": 0.00392, "n2": 0.00392}, "middle": {"p": 0.0025, "n1": 0.0025, "n2": 0.0025}}}, "E_c": 5144190.898479565, "lambda_cw": 1.0, "n": 5.637426870875134, "f_r": 318.1980515339464, "strips": {"l_1": {"column": 17.0, "middle": 17.0}, "l_2": {"column": 17.0, "middle": 17.0}}, "mass": 6677.51552795031, "weight": 215.016, "rho_max": 0.021250000000000005, "bending_moments": {"l_1": {"service": {"column": {"n1": {"dl": 189.9, "ll": 86.8}, "n2": {"dl": 383.4, "ll": 175.2}, "p": {"dl": 227.8, "ll": 104.1}}, "middle": {"n1": {"dl": 0.0, "ll": 0.0}, "n2": {"dl": 127.8, "ll": 58.4}, "p": {"dl": 151.9, "ll": 69.4}}}, "factored": {"column": {"n1": 366.8, "n2": 740.4, "p": 439.9}, "middle": {"n1": 0.0, "n2": 246.8, "p": 293.3}}}, "l_2": {"service": {"column": {"n1": {"dl": 356.0, "ll": 162.7}, "n2": {"dl": 356.0, "ll": 162.7}, "p": {"dl": 153.3, "ll": 70.1}}, "middle": {"n1": {"dl": 118.7, "ll": 54.2}, "n2": {"dl": 118.7, "ll": 54.2}, "p": {"dl": 102.2, "ll": 46.7}}}, "factored": {"column": {"n1": 687.5, "n2": 687.5, "p": 296.1}, "middle": {"n1": 229.2, "n2": 229.2, "p": 197.4}}}}, "I_e": 53514.55, "I_g": 93296.0, "k_1": 0.5735996184187961, "f_i": 6.55497750785347, "vib": {"beta": 0.03, "very_slow": {"V_13": 1420.0, "crit": "pass"}, "slow": {"V_13": 4890.0, "crit": "pass"}, "moderate": {"V_13": 5880.0, "crit": "pass"}, "fast": {"V_13": 6278.0, "crit": "fail"}}}, {"l_1": 34, "l_2": 34, "h": 14, "f_c": 5000, "c_1": 24, "c_2": 24, "bay": {"l_1": "exterior", "l_2": "interior"}, "l_ratio": 1.0, "f_y": 60000, "w_c": 150, "nu": 0.2, "loading": {"sdl": 0, "ll_design": 80, "ll_vib": 11}, "reinforcement": {"type": "estimated"}, "phi": 0.9, "rho": {"l_1": {"column": {"p": 0.00261, "n1": 0.0025, "n2": 0.0044}, "middle": {"p": 0.0025, "n1": 0.0025, "n2": 0.0025}}, "l_2": {"column": {"p": 0.0025, "n1": 0.00408, "n2": 0.00408}, "middle": {"p": 0.0025, "n1": 0.0025, "n2": 0.0025}}}, "E_c": 5144190.898479565, "lambda_cw": 1.0, "n": 5.637426870875134, "f_r": 318.1980515339464, "strips": {"l_1": {"column": 17.0, "middle": 17.0}, "l_2": {"column": 17.0, "middle": 17.0}}, "mass": 6677.51552795031, "weight": 215.016, "rho_max": 0.021250000000000005, "bending_moments": {"l_1": {"service": {"column": {"n1": {"dl": 198.0, "ll": 90.5}, "n2": {"dl": 399.8, "ll": 182.8}, "p": {"dl": 237.6, "ll": 108.6}}, "middle": {"n1": {"dl": 0.0, "ll": 0.0}, "n2": {"dl": 133.3, "ll": 60.9}, "p": {"dl": 158.4, "ll": 72.4}}}, "factored": {"column": {"n1": 382.4, "n2": 772.2, "p": 458.9}, "middle": {"n1": 0.0, "n2": 257.4, "p": 305.9}}}, "l_2": {"service": {"column": {"n1": {"dl": 371.3, "ll": 169.7}, "n2": {"dl": 371.3, "ll": 169.7}, "p": {"dl": 159.9, "ll": 73.1}}, "middle": {"n1": {"dl": 123.8, "ll": 56.6}, "n2": {"dl": 123.8, "ll": 56.6}, "p": {"dl": 106.6, "ll": 48.7}}}, "factored": {"column": {"n1": 717.1, "n2": 717.1, "p": 308.8}, "middle": {"n1": 239.1, "n2": 239.1, "p": 205.8}}}}, "I_e": 49871.95, "I_g": 93296.0, "k_1": 0.5345561438861258, "f_i": 5.7252934044560515, "vib": {"beta": 0.03, "very_slow": {"V_13": 1665.0, "crit": "pass"}, "slow": {"V_13": 6391.0, "crit": "fail"}, "moderate": {"V_13": 6768.0, "crit": "fail"}, "fast": {"V_13": 7167.0, "crit": "fail"}}}, {"l_1": 34, "l_2": 34, "h": 14, "f_c": 5000, "c_1": 26, "c_2": 26, "bay": {"l_1": "exterior", "l_2": "interior"}, "l_ratio": 1.0, "f_y": 60000, "w_c": 150, "nu": 0.2, "loading": {"sdl": 0, "ll_design": 80, "ll_vib": 11}, "reinforcement": {"type": "estimated"}, "phi": 0.9, "rho": {"l_1": {"column": {"p": 0.00259, "n1": 0.0025, "n2": 0.00435}, "middle": {"p": 0.0025, "n1": 0.0025, "n2": 0.0025}}, "l_2": {"column": {"p": 0.0025, "n1": 0.00404, "n2": 0.00404}, "middle": {"p": 0.0025, "n1": 0.0025, "n2": 0.0025}}}, "E_c": 5144190.898479565, "lambda_cw": 1.0, "n": 5.637426870875134, "f_r": 318.1980515339464, "strips": {"l_1": {"column": 17.0, "middle": 17.0}, "l_2": {"column": 17.0, "middle": 17.0}}, "mass": 6677.51552795031, "weight": 215.016, "rho_max": 0.021250000000000005, "bending_moments": {"l_1": {"service": {"column": {"n1": {"dl": 196.0, "ll": 89.6}, "n2": {"dl": 395.7, "ll": 180.9}, "p": {"dl": 235.2, "ll": 107.5}}, "middle": {"n1": {"dl": 0.0, "ll": 0.0}, "n2": {"dl": 131.9, "ll": 60.3}, "p": {"dl": 156.8, "ll": 71.7}}}, "factored": {"column": {"n1": 378.6, "n2": 764.3, "p": 454.2}, "middle": {"n1": 0.0, "n2": 254.8, "p": 302.9}}}, "l_2": {"service": {"column": {"n1": {"dl": 367.4, "ll": 168.0}, "n2": {"dl": 367.4, "ll": 168.0}, "p": {"dl": 158.3, "ll": 72.4}}, "middle": {"n1": {"dl": 122.5, "ll": 56.0}, "n2": {"dl": 122.5, "ll": 56.0}, "p": {"dl": 105.5, "ll": 48.2}}}, "factored": {"column": {"n1": 709.7, "n2": 709.7, "p": 305.8}, "middle": {"n1": 236.6, "n2": 236.6, "p": 203.7}}}}, "I_e": 51443.149999999994, "I_g": 93296.0, "k_1": 0.5513971660092608, "f_i": 6.426863022653249, "vib": {"beta": 0.03, "very_slow": {"V_13": 1452.0, "crit": "pass"}, "slow": {"V_13": 5150.0, "crit": "pass"}, "moderate": {"V_13": 5999.0, "crit": "pass"}, "fast": {"V_13": 6397.0, "crit": "fail"}}}, {"l_1": 34, "l_2": 34, "h": 14, "f_c": 5000, "c_1": 28, "c_2": 28, "bay": {"l_1": "exterior", "l_2": "interior"}, "l_ratio": 1.0, "f_y": 60000, "w_c": 150, "nu": 0.2, "loading": {"sdl": 0, "ll_design": 80, "ll_vib": 11}, "reinforcement": {"type": "estimated"}, "phi": 0.9, "rho": {"l_1": {"column": {"p": 0.00256, "n1": 0.0025, "n2": 0.00431}, "middle": {"p": 0.0025, "n1": 0.0025, "n2": 0.0025}}, "l_2": {"column": {"p": 0.0025, "n1": 0.004, "n2": 0.004}, "middle": {"p": 0.0025, "n1": 0.0025, "n2": 0.0025}}}, "E_c": 5144190.898479565, "lambda_cw": 1.0, "n": 5.637426870875134, "f_r": 318.1980515339464, "strips": {"l_1": {"column": 17.0, "middle": 17.0}, "l_2": {"column": 17.0, "middle": 17.0}}, "mass": 6677.51552795031, "weight": 215.016, "rho_max": 0.021250000000000005, "bending_moments": {"l_1": {"service": {"column": {"n1": {"dl": 193.9, "ll": 88.6}, "n2": {"dl": 391.6, "ll": 179.0}, "p": {"dl": 232.7, "ll": 106.4}}, "middle": {"n1": {"dl": 0.0, "ll": 0.0}, "n2": {"dl": 130.5, "ll": 59.7}, "p": {"dl": 155.1, "ll": 70.9}}}, "factored": {"column": {"n1": 374.4, "n2": 756.3, "p": 449.5}, "middle": {"n1": 0.0, "n2": 252.1, "p": 299.6}}}, "l_2": {"service": {"column": {"n1": {"dl": 363.6, "ll": 166.2}, "n2": {"dl": 363.6, "ll": 166.2}, "p": {"dl": 156.6, "ll": 71.6}}, "middle": {"n1": {"dl": 121.2, "ll": 55.4}, "n2": {"dl": 121.2, "ll": 55.4}, "p": {"dl": 104.4, "ll": 47.7}}}, "factored": {"column": {"n1": 702.2, "n2": 702.2, "p": 302.5}, "middle": {"n1": 234.1, "n2": 234.1, "p": 201.6}}}}, "I_e": 53523.2, "I_g": 93296.0, "k_1": 0.5736923340764877, "f_i": 6.55550725410363, "vib": {"beta": 0.03, "very_slow": {"V_13": 1417.0, "crit": "pass"}, "slow": {"V_13": 4869.0, "crit": "pass"}, "moderate": {"V_13": 5870.0, "crit": "pass"}, "fast": {"V_13": 6268.0, "crit": "fail"}}}, {"l_1": 34, "l_2": 34, "h": 14, "f_c": 5000, "c_1": 30, "c_2": 30, "bay": {"l_1": "exterior", "l_2": "interior"}, "l_ratio": 1.0, "f_y": 60000, "w_c": 150, "nu": 0.2, "loading": {"sdl": 0, "ll_design": 80, "ll_vib": 11}, "reinforcement": {"type": "estimated"}, "phi": 0.9, "rho": {"l_1": {"column": {"p": 0.00253, "n1": 0.0025, "n2": 0.00426}, "middle": {"p": 0.0025, "n1": 0.0025, "n2": 0.0025}}, "l_2": {"column": {"p": 0.0025, "n1": 0.00396, "n2": 0.00396}, "middle": {"p": 0.0025, "n1": 0.0025, "n2": 0.0025}}}, "E_c": 5144190.898479565, "lambda_cw": 1.0, "n": 5.637426870875134, "f_r": 318.1980515339464, "strips": {"l_1": {"column": 17.0, "middle": 17.0}, "l_2": {"column": 17.0, "middle": 17.0}}, "mass": 6677.51552795031, "weight": 215.016, "rho_max": 0.021250000000000005, "bending_moments": {"l_1": {"service": {"column": {"n1": {"dl": 191.9, "ll": 87.7}, "n2": {"dl": 387.4, "ll": 177.1}, "p": {"dl": 230.3, "ll": 105.3}}, "middle": {"n1": {"dl": 0.0, "ll": 0.0}, "n2": {"dl": 129.1, "ll": 59.0}, "p": {"dl": 153.5, "ll": 70.2}}}, "factored": {"column": {"n1": 370.6, "n2": 748.2, "p": 444.8}, "middle": {"n1": 0.0, "n2": 249.3, "p": 296.5}}}, "l_2": {"service": {"column": {"n1": {"dl": 359.8, "ll": 164.5}, "n2": {"dl": 359.8, "ll": 164.5}, "p": {"dl": 155.0, "ll": 70.8}}, "middle": {"n1": {"dl": 119.9, "ll": 54.8}, "n2": {"dl": 119.9, "ll": 54.8}, "p": {"dl": 103.3, "ll": 47.2}}}, "factored": {"column": {"n1": 695.0, "n2": 695.0, "p": 299.3}, "middle": {"n1": 231.6, "n2": 231.6, "p": 199.5}}}}, "I_e": 53516.3, "I_g": 93296.0, "k_1": 0.5736183759217973, "f_i": 6.5550846854048, "vib": {"beta": 0.03, "very_slow": {"V_13": 1417.0, "crit": "pass"}, "slow": {"V_13": 4869.0, "crit": "pass"}, "moderate": {"V_13": 5870.0, "crit": "pass"}, "fast": {"V_13": 6268.0, "crit": "fail"}}}, {"l_1": 34, "l_2": 34, "h": 14, "f_c": 5000, "c_1": 32, "c_2": 32, "bay": {"l_1": "exterior", "l_2": "interior"}, "l_ratio": 1.0, "f_y": 60000, "w_c": 150, "nu": 0.2, "loading": {"sdl": 0, "ll_design": 80, "ll_vib": 11}, "reinforcement": {"type": "estimated"}, "phi": 0.9, "rho": {"l_1": {"column": {"p": 0.00251, "n1": 0.0025, "n2": 0.00422}, "middle": {"p": 0.0025, "n1": 0.0025, "n2": 0.0025}}, "l_2": {"column": {"p": 0.0025, "n1": 0.00392, "n2": 0.00392}, "middle": {"p": 0.0025, "n1": 0.0025, "n2": 0.0025}}}, "E_c": 5144190.898479565, "lambda_cw": 1.0, "n": 5.637426870875134, "f_r": 318.1980515339464, "strips": {"l_1": {"column": 17.0, "middle": 17.0}, "l_2": {"column": 17.0, "middle": 17.0}}, "mass": 6677.51552795031, "weight": 215.016, "rho_max": 0.021250000000000005, "bending_moments": {"l_1": {"service": {"column": {"n1": {"dl": 189.9, "ll": 86.8}, "n2": {"dl": 383.4, "ll": 175.2}, "p": {"dl": 227.8, "ll": 104.1}}, "middle": {"n1": {"dl": 0.0, "ll": 0.0}, "n2": {"dl": 127.8, "ll": 58.4}, "p": {"dl": 151.9, "ll": 69.4}}}, "factored": {"column": {"n1": 366.8, "n2": 740.4, "p": 439.9}, "middle": {"n1": 0.0, "n2": 246.8, "p": 293.3}}}, "l_2": {"service": {"column": {"n1": {"dl": 356.0, "ll": 162.7}, "n2": {"dl": 356.0, "ll": 162.7}, "p": {"dl": 153.3, "ll": 70.1}}, "middle": {"n1": {"dl": 118.7, "ll": 54.2}, "n2": {"dl": 118.7, "ll": 54.2}, "p": {"dl": 102.2, "ll": 46.7}}}, "factored": {"column": {"n1": 687.5, "n2": 687.5, "p": 296.1}, "middle": {"n1": 229.2, "n2": 229.2, "p": 197.4}}}}, "I_e": 53514.55, "I_g": 93296.0, "k_1": 0.5735996184187961, "f_i": 6.55497750785347, "vib": {"beta": 0.03, "very_slow": {"V_13": 1420.0, "crit": "pass"}, "slow": {"V_13": 4890.0, "crit": "pass"}, "moderate": {"V_13": 5880.0, "crit": "pass"}, "fast": {"V_13": 6278.0, "crit": "fail"}}}, {"l_1": 34, "l_2": 34, "h": 15, "f_c": 5000, "c_1": 24, "c_2": 24, "bay": {"l_1": "exterior", "l_2": "interior"}, "l_ratio": 1.0, "f_y": 60000, "w_c": 150, "nu": 0.2, "loading": {"sdl": 0, "ll_design": 80, "ll_vib": 11}, "reinforcement": {"type": "estimated"}, "phi": 0.9, "rho": {"l_1": {"column": {"p": 0.0025, "n1": 0.0025, "n2": 0.00395}, "middle": {"p": 0.0025, "n1": 0.0025, "n2": 0.0025}}, "l_2": {"column": {"p": 0.0025, "n1": 0.00367, "n2": 0.00367}, "middle": {"p": 0.0025, "n1": 0.0025, "n2": 0.0025}}}, "E_c": 5144190.898479565, "lambda_cw": 1.0, "n": 5.637426870875134, "f_r": 318.1980515339464, "strips": {"l_1": {"column": 17.0, "middle": 17.0}, "l_2": {"column": 17.0, "middle": 17.0}}, "mass": 7126.273291925465, "weight": 229.466, "rho_max": 0.021250000000000005, "bending_moments": {"l_1": {"service": {"column": {"n1": {"dl": 212.2, "ll": 90.5}, "n2": {"dl": 428.4, "ll": 182.8}, "p": {"dl": 254.6, "ll": 108.6}}, "middle": {"n1": {"dl": 0.0, "ll": 0.0}, "n2": {"dl": 142.8, "ll": 60.9}, "p": {"dl": 169.7, "ll": 72.4}}}, "factored": {"column": {"n1": 399.4, "n2": 806.6, "p": 479.3}, "middle": {"n1": 0.0, "n2": 268.8, "p": 319.5}}}, "l_2": {"service": {"column": {"n1": {"dl": 397.8, "ll": 169.7}, "n2": {"dl": 397.8, "ll": 169.7}, "p": {"dl": 171.4, "ll": 73.1}}, "middle": {"n1": {"dl": 132.6, "ll": 56.6}, "n2": {"dl": 132.6, "ll": 56.6}, "p": {"dl": 114.2, "ll": 48.7}}}, "factored": {"column": {"n1": 748.9, "n2": 748.9, "p": 322.6}, "middle": {"n1": 249.7, "n2": 249.7, "p": 215.0}}}}, "I_e": 66181.8, "I_g": 114750.0, "k_1": 0.5767477124183007, "f_i": 6.384326323733991, "vib": {"beta": 0.03, "very_slow": {"V_13": 1373.0, "crit": "pass"}, "slow": {"V_13": 4926.0, "crit": "pass"}, "moderate": {"V_13": 5667.0, "crit": "pass"}, "fast": {"V_13": 6040.0, "crit": "fail"}}}, {"l_1": 34, "l_2": 34, "h": 15, "f_c": 5000, "c_1": 26, "c_2": 26, "bay": {"l_1": "exterior", "l_2": "interior"}, "l_ratio": 1.0, "f_y": 60000, "w_c": 150, "nu": 0.2, "loading": {"sdl": 0, "ll_design": 80, "ll_vib": 11}, "reinforcement": {"type": "estimated"}, "phi": 0.9, "rho": {"l_1": {"column": {"p": 0.0025, "n1": 0.0025, "n2": 0.00391}, "middle": {"p": 0.0025, "n1": 0.0025, "n2": 0.0025}}, "l_2": {"column": {"p": 0.0025, "n1": 0.00363, "n2": 0.00363}, "middle": {"p": 0.0025, "n1": 0.0025, "n2": 0.0025}}}, "E_c": 5144190.898479565, "lambda_cw": 1.0, "n": 5.637426870875134, "f_r": 318.1980515339464, "strips": {"l_1": {"column": 17.0, "middle": 17.0}, "l_2": {"column": 17.0, "middle": 17.0}}, "mass": 7126.273291925465, "weight": 229.466, "rho_max": 0.021250000000000005, "bending_moments": {"l_1": {"service": {"column": {"n1": {"dl": 210.0, "ll": 89.6}, "n2": {"dl": 423.9, "ll": 180.9}, "p": {"dl": 251.9, "ll": 107.5}}, "middle": {"n1": {"dl": 0.0, "ll": 0.0}, "n2": {"dl": 141.3, "ll": 60.3}, "p": {"dl": 168.0, "ll": 71.7}}}, "factored": {"column": {"n1": 395.4, "n2": 798.1, "p": 474.3}, "middle": {"n1": 0.0, "n2": 266.0, "p": 316.3}}}, "l_2": {"service": {"column": {"n1": {"dl": 393.7, "ll": 168.0}, "n2": {"dl": 393.7, "ll": 168.0}, "p": {"dl": 169.6, "ll": 72.4}}, "middle": {"n1": {"dl": 131.2, "ll": 56.0}, "n2": {"dl": 131.2, "ll": 56.0}, "p": {"dl": 113.1, "ll": 48.2}}}, "factored": {"column": {"n1": 741.2, "n2": 741.2, "p": 319.4}, "middle": {"n1": 247.0, "n2": 247.0, "p": 212.8}}}}, "I_e": 66240.9, "I_g": 114750.0, "k_1": 0.5772627450980392, "f_i": 7.059510617057628, "vib": {"beta": 0.03, "very_slow": {"V_13": 1213.0, "crit": "pass"}, "slow": {"V_13": 3549.0, "crit": "pass"}, "moderate": {"V_13": 5019.0, "crit": "pass"}, "fast": {"V_13": 5438.0, "crit": "pass"}}}, {"l_1": 34, "l_2": 34, "h": 15, "f_c": 5000, "c_1": 28, "c_2": 28, "bay": {"l_1": "exterior", "l_2": "interior"}, "l_ratio": 1.0, "f_y": 60000, "w_c": 150, "nu": 0.2, "loading": {"sdl": 0, "ll_design": 80, "ll_vib": 11}, "reinforcement": {"type": "estimated"}, "phi": 0.9, "rho": {"l_1": {"column": {"p": 0.0025, "n1": 0.0025, "n2": 0.00387}, "middle": {"p": 0.0025, "n1": 0.0025, "n2": 0.0025}}, "l_2": {"column": {"p": 0.0025, "n1": 0.00359, "n2": 0.00359}, "middle": {"p": 0.0025, "n1": 0.0025, "n2": 0.0025}}}, "E_c": 5144190.898479565, "lambda_cw": 1.0, "n": 5.637426870875134, "f_r": 318.1980515339464, "strips": {"l_1": {"column": 17.0, "middle": 17.0}, "l_2": {"column": 17.0, "middle": 17.0}}, "mass": 7126.273291925465, "weight": 229.466, "rho_max": 0.021250000000000005, "bending_moments": {"l_1": {"service": {"column": {"n1": {"dl": 207.8, "ll": 88.6}, "n2": {"dl": 419.5, "ll": 179.0}, "p": {"dl": 249.3, "ll": 106.4}}, "middle": {"n1": {"dl": 0.0, "ll": 0.0}, "n2": {"dl": 139.8, "ll": 59.7}, "p": {"dl": 166.2, "ll": 70.9}}}, "factored": {"column": {"n1": 391.1, "n2": 789.8, "p": 469.4}, "middle": {"n1": 0.0, "n2": 263.3, "p": 312.9}}}, "l_2": {"service": {"column": {"n1": {"dl": 389.6, "ll": 166.2}, "n2": {"dl": 389.6, "ll": 166.2}, "p": {"dl": 167.8, "ll": 71.6}}, "middle": {"n1": {"dl": 129.9, "ll": 55.4}, "n2": {"dl": 129.9, "ll": 55.4}, "p": {"dl": 111.9, "ll": 47.7}}}, "factored": {"column": {"n1": 733.4, "n2": 733.4, "p": 315.9}, "middle": {"n1": 244.5, "n2": 244.5, "p": 210.6}}}}, "I_e": 66304.7, "I_g": 114750.0, "k_1": 0.5778187363834423, "f_i": 7.062909486785534, "vib": {"beta": 0.03, "very_slow": {"V_13": 1213.0, "crit": "pass"}, "slow": {"V_13": 3549.0, "crit": "pass"}, "moderate": {"V_13": 5019.0, "crit": "pass"}, "fast": {"V_13": 5438.0, "crit": "pass"}}}, {"l_1": 34, "l_2": 34, "h": 15, "f_c": 5000, "c_1": 30, "c_2": 30, "bay": {"l_1": "exterior", "l_2": "interior"}, "l_ratio": 1.0, "f_y": 60000, "w_c": 150, "nu": 0.2, "loading": {"sdl": 0, "ll_design": 80, "ll_vib": 11}, "reinforcement": {"type": "estimated"}, "phi": 0.9, "rho": {"l_1": {"column": {"p": 0.0025, "n1": 0.0025, "n2": 0.00383}, "middle": {"p": 0.0025, "n1": 0.0025, "n2": 0.0025}}, "l_2": {"column": {"p": 0.0025, "n1": 0.00355, "n2": 0.00355}, "middle": {"p": 0.0025, "n1": 0.0025, "n2": 0.0025}}}, "E_c": 5144190.898479565, "lambda_cw": 1.0, "n": 5.637426870875134, "f_r": 318.1980515339464, "strips": {"l_1": {"column": 17.0, "middle": 17.0}, "l_2": {"column": 17.0, "middle": 17.0}}, "mass": 7126.273291925465, "weight": 229.466, "rho_max": 0.021250000000000005, "bending_moments": {"l_1": {"service": {"column": {"n1": {"dl": 205.6, "ll": 87.7}, "n2": {"dl": 415.1, "ll": 177.1}, "p": {"dl": 246.7, "ll": 105.3}}, "middle": {"n1": {"dl": 0.0, "ll": 0.0}, "n2": {"dl": 138.4, "ll": 59.0}, "p": {"dl": 164.5, "ll": 70.2}}}, "factored": {"column": {"n1": 387.0, "n2": 781.5, "p": 464.5}, "middle": {"n1": 0.0, "n2": 260.5, "p": 309.7}}}, "l_2": {"service": {"column": {"n1": {"dl": 385.5, "ll": 164.5}, "n2": {"dl": 385.5, "ll": 164.5}, "p": {"dl": 166.0, "ll": 70.8}}, "middle": {"n1": {"dl": 128.5, "ll": 54.8}, "n2": {"dl": 128.5, "ll": 54.8}, "p": {"dl": 110.7, "ll": 47.2}}}, "factored": {"column": {"n1": 725.8, "n2": 725.8, "p": 312.5}, "middle": {"n1": 241.9, "n2": 241.9, "p": 208.4}}}}, "I_e": 66371.5, "I_g": 114750.0, "k_1": 0.578400871459695, "f_i": 7.066466426051175, "vib": {"beta": 0.03, "very_slow": {"V_13": 1211.0, "crit": "pass"}, "slow": {"V_13": 3528.0, "crit": "pass"}, "moderate": {"V_13": 5003.0, "crit": "pass"}, "fast": {"V_13": 5430.0, "crit": "pass"}}}, {"l_1": 34, "l_2": 34, "h": 15, "f_c": 5000, "c_1": 32, "c_2": 32, "bay": {"l_1": "exterior", "l_2": "interior"}, "l_ratio": 1.0, "f_y": 60000, "w_c": 150, "nu": 0.2, "loading": {"sdl": 0, "ll_design": 80, "ll_vib": 11}, "reinforcement": {"type": "estimated"}, "phi": 0.9, "rho": {"l_1": {"column": {"p": 0.0025, "n1": 0.0025, "n2": 0.00379}, "middle": {"p": 0.0025, "n1": 0.0025, "n2": 0.0025}}, "l_2": {"column": {"p": 0.0025, "n1": 0.00352, "n2": 0.00352}, "middle": {"p": 0.0025, "n1": 0.0025, "n2": 0.0025}}}, "E_c": 5144190.898479565, "lambda_cw": 1.0, "n": 5.637426870875134, "f_r": 318.1980515339464, "strips": {"l_1": {"column": 17.0, "middle": 17.0}, "l_2": {"column": 17.0, "middle": 17.0}}, "mass": 7126.273291925465, "weight": 229.466, "rho_max": 0.021250000000000005, "bending_moments": {"l_1": {"service": {"column": {"n1": {"dl": 203.4, "ll": 86.8}, "n2": {"dl": 410.7, "ll": 175.2}, "p": {"dl": 244.1, "ll": 104.1}}, "middle": {"n1": {"dl": 0.0, "ll": 0.0}, "n2": {"dl": 136.9, "ll": 58.4}, "p": {"dl": 162.7, "ll": 69.4}}}, "factored": {"column": {"n1": 383.0, "n2": 773.2, "p": 459.5}, "middle": {"n1": 0.0, "n2": 257.7, "p": 306.3}}}, "l_2": {"service": {"column": {"n1": {"dl": 381.4, "ll": 162.7}, "n2": {"dl": 381.4, "ll": 162.7}, "p": {"dl": 164.3, "ll": 70.1}}, "middle": {"n1": {"dl": 127.1, "ll": 54.2}, "n2": {"dl": 127.1, "ll": 54.2}, "p": {"dl": 109.5, "ll": 46.7}}}, "factored": {"column": {"n1": 718.0, "n2": 718.0, "p": 309.3}, "middle": {"n1": 239.2, "n2": 239.2, "p": 206.1}}}}, "I_e": 66442.95, "I_g": 114750.0, "k_1": 0.5790235294117647, "f_i": 7.070268986007085, "vib": {"beta": 0.03, "very_slow": {"V_13": 1211.0, "crit": "pass"}, "slow": {"V_13": 3528.0, "crit": "pass"}, "moderate": {"V_13": 5003.0, "crit": "pass"}, "fast": {"V_13": 5430.0, "crit": "pass"}}}, {"l_1": 34, "l_2": 34, "h": 16, "f_c": 5000, "c_1": 24, "c_2": 24, "bay": {"l_1": "exterior", "l_2": "interior"}, "l_ratio": 1.0, "f_y": 60000, "w_c": 150, "nu": 0.2, "loading": {"sdl": 0, "ll_design": 80, "ll_vib": 11}, "reinforcement": {"type": "estimated"}, "phi": 0.9, "rho": {"l_1": {"column": {"p": 0.0025, "n1": 0.0025, "n2": 0.00358}, "middle": {"p": 0.0025, "n1": 0.0025, "n2": 0.0025}}, "l_2": {"column": {"p": 0.0025, "n1": 0.00332, "n2": 0.00332}, "middle": {"p": 0.0025, "n1": 0.0025, "n2": 0.0025}}}, "E_c": 5144190.898479565, "lambda_cw": 1.0, "n": 5.637426870875134, "f_r": 318.1980515339464, "strips": {"l_1": {"column": 17.0, "middle": 17.0}, "l_2": {"column": 17.0, "middle": 17.0}}, "mass": 7575.03105590062, "weight": 243.916, "rho_max": 0.021250000000000005, "bending_moments": {"l_1": {"service": {"column": {"n1": {"dl": 226.3, "ll": 90.5}, "n2": {"dl": 457.0, "ll": 182.8}, "p": {"dl": 271.6, "ll": 108.6}}, "middle": {"n1": {"dl": 0.0, "ll": 0.0}, "n2": {"dl": 152.3, "ll": 60.9}, "p": {"dl": 181.0, "ll": 72.4}}}, "factored": {"column": {"n1": 416.4, "n2": 840.9, "p": 499.7}, "middle": {"n1": 0.0, "n2": 280.2, "p": 333.0}}}, "l_2": {"service": {"column": {"n1": {"dl": 424.3, "ll": 169.7}, "n2": {"dl": 424.3, "ll": 169.7}, "p": {"dl": 182.8, "ll": 73.1}}, "middle": {"n1": {"dl": 141.4, "ll": 56.6}, "n2": {"dl": 141.4, "ll": 56.6}, "p": {"dl": 121.9, "ll": 48.7}}}, "factored": {"column": {"n1": 780.7, "n2": 780.7, "p": 336.3}, "middle": {"n1": 260.2, "n2": 260.2, "p": 224.2}}}}, "I_e": 81178.55, "I_g": 139264.0, "k_1": 0.5829112333409927, "f_i": 6.858126041028521, "vib": {"beta": 0.03, "very_slow": {"V_13": 1183.0, "crit": "pass"}, "slow": {"V_13": 3720.0, "crit": "pass"}, "moderate": {"V_13": 4925.0, "crit": "pass"}, "fast": {"V_13": 5275.0, "crit": "pass"}}}, {"l_1": 34, "l_2": 34, "h": 16, "f_c": 5000, "c_1": 26, "c_2": 26, "bay": {"l_1": "exterior", "l_2": "interior"}, "l_ratio": 1.0, "f_y": 60000, "w_c": 150, "nu": 0.2, "loading": {"sdl": 0, "ll_design": 80, "ll_vib": 11}, "reinforcement": {"type": "estimated"}, "phi": 0.9, "rho": {"l_1": {"column": {"p": 0.0025, "n1": 0.0025, "n2": 0.00354}, "middle": {"p": 0.0025, "n1": 0.0025, "n2": 0.0025}}, "l_2": {"column": {"p": 0.0025, "n1": 0.00329, "n2": 0.00329}, "middle": {"p": 0.0025, "n1": 0.0025, "n2": 0.0025}}}, "E_c": 5144190.898479565, "lambda_cw": 1.0, "n": 5.637426870875134, "f_r": 318.1980515339464, "strips": {"l_1": {"column": 17.0, "middle": 17.0}, "l_2": {"column": 17.0, "middle": 17.0}}, "mass": 7575.03105590062, "weight": 243.916, "rho_max": 0.021250000000000005, "bending_moments": {"l_1": {"service": {"column": {"n1": {"dl": 224.0, "ll": 89.6}, "n2": {"dl": 452.2, "ll": 180.9}, "p": {"dl": 268.7, "ll": 107.5}}, "middle": {"n1": {"dl": 0.0, "ll": 0.0}, "n2": {"dl": 150.7, "ll": 60.3}, "p": {"dl": 179.2, "ll": 71.7}}}, "factored": {"column": {"n1": 412.2, "n2": 832.1, "p": 494.4}, "middle": {"n1": 0.0, "n2": 277.3, "p": 329.8}}}, "l_2": {"service": {"column": {"n1": {"dl": 419.9, "ll": 168.0}, "n2": {"dl": 419.9, "ll": 168.0}, "p": {"dl": 180.9, "ll": 72.4}}, "middle": {"n1": {"dl": 140.0, "ll": 56.0}, "n2": {"dl": 140.0, "ll": 56.0}, "p": {"dl": 120.6, "ll": 48.2}}}, "factored": {"column": {"n1": 772.7, "n2": 772.7, "p": 332.9}, "middle": {"n1": 257.6, "n2": 257.6, "p": 221.8}}}}, "I_e": 81289.85, "I_g": 139264.0, "k_1": 0.5837104348575368, "f_i": 7.585228575261153, "vib": {"beta": 0.03, "very_slow": {"V_13": 1043.0, "crit": "pass"}, "slow": {"V_13": 2328.0, "crit": "pass"}, "moderate": {"V_13": 3911.0, "crit": "pass"}, "fast": {"V_13": 4730.0, "crit": "pass"}}}, {"l_1": 34, "l_2": 34, "h": 16, "f_c": 5000, "c_1": 28, "c_2": 28, "bay": {"l_1": "exterior", "l_2": "interior"}, "l_ratio": 1.0, "f_y": 60000, "w_c": 150, "nu": 0.2, "loading": {"sdl": 0, "ll_design": 80, "ll_vib": 11}, "reinforcement": {"type": "estimated"}, "phi": 0.9, "rho": {"l_1": {"column": {"p": 0.0025, "n1": 0.0025, "n2": 0.0035}, "middle": {"p": 0.0025, "n1": 0.0025, "n2": 0.0025}}, "l_2": {"column": {"p": 0.0025, "n1": 0.00325, "n2": 0.00325}, "middle": {"p": 0.0025, "n1": 0.0025, "n2": 0.0025}}}, "E_c": 5144190.898479565, "lambda_cw": 1.0, "n": 5.637426870875134, "f_r": 318.1980515339464, "strips": {"l_1": {"column": 17.0, "middle": 17.0}, "l_2": {"column": 17.0, "middle": 17.0}}, "mass": 7575.03105590062, "weight": 243.916, "rho_max": 0.021250000000000005, "bending_moments": {"l_1": {"service": {"column": {"n1": {"dl": 221.6, "ll": 88.6}, "n2": {"dl": 447.5, "ll": 179.0}, "p": {"dl": 265.9, "ll": 106.4}}, "middle": {"n1": {"dl": 0.0, "ll": 0.0}, "n2": {"dl": 149.2, "ll": 59.7}, "p": {"dl": 177.3, "ll": 70.9}}}, "factored": {"column": {"n1": 407.7, "n2": 823.4, "p": 489.3}, "middle": {"n1": 0.0, "n2": 274.6, "p": 326.2}}}, "l_2": {"service": {"column": {"n1": {"dl": 415.5, "ll": 166.2}, "n2": {"dl": 415.5, "ll": 166.2}, "p": {"dl": 179.0, "ll": 71.6}}, "middle": {"n1": {"dl": 138.5, "ll": 55.4}, "n2": {"dl": 138.5, "ll": 55.4}, "p": {"dl": 119.3, "ll": 47.7}}}, "factored": {"column": {"n1": 764.5, "n2": 764.5, "p": 329.4}, "middle": {"n1": 254.8, "n2": 254.8, "p": 219.5}}}}, "I_e": 81408.15, "I_g": 139264.0, "k_1": 0.5845599006204044, "f_i": 7.59074590804542, "vib": {"beta": 0.03, "very_slow": {"V_13": 1043.0, "crit": "pass"}, "slow": {"V_13": 2328.0, "crit": "pass"}, "moderate": {"V_13": 3911.0, "crit": "pass"}, "fast": {"V_13": 4730.0, "crit": "pass"}}}, {"l_1": 34, "l_2": 34, "h": 16, "f_c": 5000, "c_1": 30, "c_2": 30, "bay": {"l_1": "exterior", "l_2": "interior"}, "l_ratio": 1.0, "f_y": 60000, "w_c": 150, "nu": 0.2, "loading": {"sdl": 0, "ll_design": 80, "ll_vib": 11}, "reinforcement": {"type": "estimated"}, "phi": 0.9, "rho": {"l_1": {"column": {"p": 0.0025, "n1": 0.0025, "n2": 0.00347}, "middle": {"p": 0.0025, "n1": 0.0025, "n2": 0.0025}}, "l_2": {"column": {"p": 0.0025, "n1": 0.00322, "n2": 0.00322}, "middle": {"p": 0.0025, "n1": 0.0025, "n2": 0.0025}}}, "E_c": 5144190.898479565, "lambda_cw": 1.0, "n": 5.637426870875134, "f_r": 318.1980515339464, "strips": {"l_1": {"column": 17.0, "middle": 17.0}, "l_2": {"column": 17.0, "middle": 17.0}}, "mass": 7575.03105590062, "weight": 243.916, "rho_max": 0.021250000000000005, "bending_moments": {"l_1": {"service": {"column": {"n1": {"dl": 219.3, "ll": 87.7}, "n2": {"dl": 442.8, "ll": 177.1}, "p": {"dl": 263.1, "ll": 105.3}}, "middle": {"n1": {"dl": 0.0, "ll": 0.0}, "n2": {"dl": 147.6, "ll": 59.0}, "p": {"dl": 175.4, "ll": 70.2}}}, "factored": {"column": {"n1": 403.5, "n2": 814.7, "p": 484.2}, "middle": {"n1": 0.0, "n2": 271.5, "p": 322.8}}}, "l_2": {"service": {"column": {"n1": {"dl": 411.2, "ll": 164.5}, "n2": {"dl": 411.2, "ll": 164.5}, "p": {"dl": 177.1, "ll": 70.8}}, "middle": {"n1": {"dl": 137.1, "ll": 54.8}, "n2": {"dl": 137.1, "ll": 54.8}, "p": {"dl": 118.1, "ll": 47.2}}}, "factored": {"column": {"n1": 756.6, "n2": 756.6, "p": 325.8}, "middle": {"n1": 252.2, "n2": 252.2, "p": 217.2}}}}, "I_e": 81532.75, "I_g": 139264.0, "k_1": 0.5854546042049632, "f_i": 7.596552730295011, "vib": {"beta": 0.03, "very_slow": {"V_13": 1041.0, "crit": "pass"}, "slow": {"V_13": 2309.0, "crit": "pass"}, "moderate": {"V_13": 3895.0, "crit": "pass"}, "fast": {"V_13": 4723.0, "crit": "pass"}}}, {"l_1": 34, "l_2": 34, "h": 16, "f_c": 5000, "c_1": 32, "c_2": 32, "bay": {"l_1": "exterior", "l_2": "interior"}, "l_ratio": 1.0, "f_y": 60000, "w_c": 150, "nu": 0.2, "loading": {"sdl": 0, "ll_design": 80, "ll_vib": 11}, "reinforcement": {"type": "estimated"}, "phi": 0.9, "rho": {"l_1": {"column": {"p": 0.0025, "n1": 0.0025, "n2": 0.00343}, "middle": {"p": 0.0025, "n1": 0.0025, "n2": 0.0025}}, "l_2": {"column": {"p": 0.0025, "n1": 0.00319, "n2": 0.00319}, "middle": {"p": 0.0025, "n1": 0.0025, "n2": 0.0025}}}, "E_c": 5144190.898479565, "lambda_cw": 1.0, "n": 5.637426870875134, "f_r": 318.1980515339464, "strips": {"l_1": {"column": 17.0, "middle": 17.0}, "l_2": {"column": 17.0, "middle": 17.0}}, "mass": 7575.03105590062, "weight": 243.916, "rho_max": 0.021250000000000005, "bending_moments": {"l_1": {"service": {"column": {"n1": {"dl": 217.0, "ll": 86.8}, "n2": {"dl": 438.1, "ll": 175.2}, "p": {"dl": 260.4, "ll": 104.1}}, "middle": {"n1": {"dl": 0.0, "ll": 0.0}, "n2": {"dl": 146.0, "ll": 58.4}, "p": {"dl": 173.6, "ll": 69.4}}}, "factored": {"column": {"n1": 399.3, "n2": 806.0, "p": 479.0}, "middle": {"n1": 0.0, "n2": 268.6, "p": 319.4}}}, "l_2": {"service": {"column": {"n1": {"dl": 406.8, "ll": 162.7}, "n2": {"dl": 406.8, "ll": 162.7}, "p": {"dl": 175.2, "ll": 70.1}}, "middle": {"n1": {"dl": 135.6, "ll": 54.2}, "n2": {"dl": 135.6, "ll": 54.2}, "p": {"dl": 116.8, "ll": 46.7}}}, "factored": {"column": {"n1": 748.5, "n2": 748.5, "p": 322.4}, "middle": {"n1": 249.4, "n2": 249.4, "p": 214.9}}}}, "I_e": 81665.85, "I_g": 139264.0, "k_1": 0.5864103429457721, "f_i": 7.602750784795067, "vib": {"beta": 0.03, "very_slow": {"V_13": 1041.0, "crit": "pass"}, "slow": {"V_13": 2309.0, "crit": "pass"}, "moderate": {"V_13": 3895.0, "crit": "pass"}, "fast": {"V_13": 4723.0, "crit": "pass"}}}, {"l_1": 34, "l_2": 34, "h": 17, "f_c": 5000, "c_1": 24, "c_2": 24, "bay": {"l_1": "exterior", "l_2": "interior"}, "l_ratio": 1.0, "f_y": 60000, "w_c": 150, "nu": 0.2, "loading": {"sdl": 0, "ll_design": 80, "ll_vib": 11}, "reinforcement": {"type": "estimated"}, "phi": 0.9, "rho": {"l_1": {"column": {"p": 0.0025, "n1": 0.0025, "n2": 0.00327}, "middle": {"p": 0.0025, "n1": 0.0025, "n2": 0.0025}}, "l_2": {"column": {"p": 0.0025, "n1": 0.00303, "n2": 0.00303}, "middle": {"p": 0.0025, "n1": 0.0025, "n2": 0.0025}}}, "E_c": 5144190.898479565, "lambda_cw": 1.0, "n": 5.637426870875134, "f_r": 318.1980515339464, "strips": {"l_1": {"column": 17.0, "middle": 17.0}, "l_2": {"column": 17.0, "middle": 17.0}}, "mass": 8023.7888198757755, "weight": 258.366, "rho_max": 0.021250000000000005, "bending_moments": {"l_1": {"service": {"column": {"n1": {"dl": 240.4, "ll": 90.5}, "n2": {"dl": 485.5, "ll": 182.8}, "p": {"dl": 288.5, "ll": 108.6}}, "middle": {"n1": {"dl": 0.0, "ll": 0.0}, "n2": {"dl": 161.8, "ll": 60.9}, "p": {"dl": 192.4, "ll": 72.4}}}, "factored": {"column": {"n1": 433.3, "n2": 875.1, "p": 520.0}, "middle": {"n1": 0.0, "n2": 291.6, "p": 346.7}}}, "l_2": {"service": {"column": {"n1": {"dl": 450.8, "ll": 169.7}, "n2": {"dl": 450.8, "ll": 169.7}, "p": {"dl": 194.2, "ll": 73.1}}, "middle": {"n1": {"dl": 150.3, "ll": 56.6}, "n2": {"dl": 150.3, "ll": 56.6}, "p": {"dl": 129.5, "ll": 48.7}}}, "factored": {"column": {"n1": 812.5, "n2": 812.5, "p": 350.0}, "middle": {"n1": 270.9, "n2": 270.9, "p": 233.3}}}}, "I_e": 98752.65, "I_g": 167042.0, "k_1": 0.5911845523880221, "f_i": 7.349565433968405, "vib": {"beta": 0.03, "very_slow": {"V_13": 1025.0, "crit": "pass"}, "slow": {"V_13": 2630.0, "crit": "pass"}, "moderate": {"V_13": 4038.0, "crit": "pass"}, "fast": {"V_13": 4625.0, "crit": "pass"}}}, {"l_1": 34, "l_2": 34, "h": 17, "f_c": 5000, "c_1": 26, "c_2": 26, "bay": {"l_1": "exterior", "l_2": "interior"}, "l_ratio": 1.0, "f_y": 60000, "w_c": 150, "nu": 0.2, "loading": {"sdl": 0, "ll_design": 80, "ll_vib": 11}, "reinforcement": {"type": "estimated"}, "phi": 0.9, "rho": {"l_1": {"column": {"p": 0.0025, "n1": 0.0025, "n2": 0.00323}, "middle": {"p": 0.0025, "n1": 0.0025, "n2": 0.0025}}, "l_2": {"column": {"p": 0.0025, "n1": 0.003, "n2": 0.003}, "middle": {"p": 0.0025, "n1": 0.0025, "n2": 0.0025}}}, "E_c": 5144190.898479565, "lambda_cw": 1.0, "n": 5.637426870875134, "f_r": 318.1980515339464, "strips": {"l_1": {"column": 17.0, "middle": 17.0}, "l_2": {"column": 17.0, "middle": 17.0}}, "mass": 8023.7888198757755, "weight": 258.366, "rho_max": 0.021250000000000005, "bending_moments": {"l_1": {"service": {"column": {"n1": {"dl": 237.9, "ll": 89.6}, "n2": {"dl": 480.5, "ll": 180.9}, "p": {"dl": 285.5, "ll": 107.5}}, "middle": {"n1": {"dl": 0.0, "ll": 0.0}, "n2": {"dl": 160.2, "ll": 60.3}, "p": {"dl": 190.4, "ll": 71.7}}}, "factored": {"column": {"n1": 428.8, "n2": 866.0, "p": 514.6}, "middle": {"n1": 0.0, "n2": 288.7, "p": 343.2}}}, "l_2": {"service": {"column": {"n1": {"dl": 446.2, "ll": 168.0}, "n2": {"dl": 446.2, "ll": 168.0}, "p": {"dl": 192.2, "ll": 72.4}}, "middle": {"n1": {"dl": 148.7, "ll": 56.0}, "n2": {"dl": 148.7, "ll": 56.0}, "p": {"dl": 128.1, "ll": 48.2}}}, "factored": {"column": {"n1": 804.2, "n2": 804.2, "p": 346.5}, "middle": {"n1": 268.0, "n2": 268.0, "p": 230.8}}}}, "I_e": 98957.15, "I_g": 167042.0, "k_1": 0.5924087953927755, "f_i": 8.131610440038296, "vib": {"beta": 0.03, "very_slow": {"V_13": 902.0, "crit": "pass"}, "slow": {"V_13": 1433.0, "crit": "pass"}, "moderate": {"V_13": 2911.0, "crit": "pass"}, "fast": {"V_13": 4055.0, "crit": "pass"}}}, {"l_1": 34, "l_2": 34, "h": 17, "f_c": 5000, "c_1": 28, "c_2": 28, "bay": {"l_1": "exterior", "l_2": "interior"}, "l_ratio": 1.0, "f_y": 60000, "w_c": 150, "nu": 0.2, "loading": {"sdl": 0, "ll_design": 80, "ll_vib": 11}, "reinforcement": {"type": "estimated"}, "phi": 0.9, "rho": {"l_1": {"column": {"p": 0.0025, "n1": 0.0025, "n2": 0.0032}, "middle": {"p": 0.0025, "n1": 0.0025, "n2": 0.0025}}, "l_2": {"column": {"p": 0.0025, "n1": 0.00297, "n2": 0.00297}, "middle": {"p": 0.0025, "n1": 0.0025, "n2": 0.0025}}}, "E_c": 5144190.898479565, "lambda_cw": 1.0, "n": 5.637426870875134, "f_r": 318.1980515339464, "strips": {"l_1": {"column": 17.0, "middle": 17.0}, "l_2": {"column": 17.0, "middle": 17.0}}, "mass": 8023.7888198757755, "weight": 258.366, "rho_max": 0.021250000000000005, "bending_moments": {"l_1": {"service": {"column": {"n1": {"dl": 235.5, "ll": 88.6}, "n2": {"dl": 475.5, "ll": 179.0}, "p": {"dl": 282.6, "ll": 106.4}}, "middle": {"n1": {"dl": 0.0, "ll": 0.0}, "n2": {"dl": 158.5, "ll": 59.7}, "p": {"dl": 188.4, "ll": 70.9}}}, "factored": {"column": {"n1": 424.4, "n2": 857.0, "p": 509.4}, "middle": {"n1": 0.0, "n2": 285.7, "p": 339.5}}}, "l_2": {"service": {"column": {"n1": {"dl": 441.5, "ll": 166.2}, "n2": {"dl": 441.5, "ll": 166.2}, "p": {"dl": 190.2, "ll": 71.6}}, "middle": {"n1": {"dl": 147.2, "ll": 55.4}, "n2": {"dl": 147.2, "ll": 55.4}, "p": {"dl": 126.8, "ll": 47.7}}}, "factored": {"column": {"n1": 795.7, "n2": 795.7, "p": 342.8}, "middle": {"n1": 265.3, "n2": 265.3, "p": 228.5}}}}, "I_e": 99173.05, "I_g": 167042.0, "k_1": 0.5937012847068402, "f_i": 8.140476187273523, "vib": {"beta": 0.03, "very_slow": {"V_13": 900.0, "crit": "pass"}, "slow": {"V_13": 1431.0, "crit": "pass"}, "moderate": {"V_13": 2897.0, "crit": "pass"}, "fast": {"V_13": 4043.0, "crit": "pass"}}}, {"l_1": 34, "l_2": 34, "h": 17, "f_c": 5000, "c_1": 30, "c_2": 30, "bay": {"l_1": "exterior", "l_2": "interior"}, "l_ratio": 1.0, "f_y": 60000, "w_c": 150, "nu": 0.2, "loading": {"sdl": 0, "ll_design": 80, "ll_vib": 11}, "reinforcement": {"type": "estimated"}, "phi": 0.9, "rho": {"l_1": {"column": {"p": 0.0025, "n1": 0.0025, "n2": 0.00317}, "middle": {"p": 0.0025, "n1": 0.0025, "n2": 0.0025}}, "l_2": {"column": {"p": 0.0025, "n1": 0.00294, "n2": 0.00294}, "middle": {"p": 0.0025, "n1": 0.0025, "n2": 0.0025}}}, "E_c": 5144190.898479565, "lambda_cw": 1.0, "n": 5.637426870875134, "f_r": 318.1980515339464, "strips": {"l_1": {"column": 17.0, "middle": 17.0}, "l_2": {"column": 17.0, "middle": 17.0}}, "mass": 8023.7888198757755, "weight": 258.366, "rho_max": 0.021250000000000005, "bending_moments": {"l_1": {"service": {"column": {"n1": {"dl": 233.0, "ll": 87.7}, "n2": {"dl": 470.5, "ll": 177.1}, "p": {"dl": 279.6, "ll": 105.3}}, "middle": {"n1": {"dl": 0.0, "ll": 0.0}, "n2": {"dl": 156.8, "ll": 59.0}, "p": {"dl": 186.4, "ll": 70.2}}}, "factored": {"column": {"n1": 419.9, "n2": 848.0, "p": 504.0}, "middle": {"n1": 0.0, "n2": 282.6, "p": 336.0}}}, "l_2": {"service": {"column": {"n1": {"dl": 436.9, "ll": 164.5}, "n2": {"dl": 436.9, "ll": 164.5}, "p": {"dl": 188.2, "ll": 70.8}}, "middle": {"n1": {"dl": 145.6, "ll": 54.8}, "n2": {"dl": 145.6, "ll": 54.8}, "p": {"dl": 125.5, "ll": 47.2}}}, "factored": {"column": {"n1": 787.5, "n2": 787.5, "p": 339.1}, "middle": {"n1": 262.4, "n2": 262.4, "p": 226.1}}}}, "I_e": 99409.8, "I_g": 167042.0, "k_1": 0.5951185929287245, "f_i": 8.15018703563853, "vib": {"beta": 0.03, "very_slow": {"V_13": 899.0, "crit": "pass"}, "slow": {"V_13": 1428.0, "crit": "pass"}, "moderate": {"V_13": 2882.0, "crit": "pass"}, "fast": {"V_13": 4031.0, "crit": "pass"}}}, {"l_1": 34, "l_2": 34, "h": 17, "f_c": 5000, "c_1": 32, "c_2": 32, "bay": {"l_1": "exterior", "l_2": "interior"}, "l_ratio": 1.0, "f_y": 60000, "w_c": 150, "nu": 0.2, "loading": {"sdl": 0, "ll_design": 80, "ll_vib": 11}, "reinforcement": {"type": "estimated"}, "phi": 0.9, "rho": {"l_1": {"column": {"p": 0.0025, "n1": 0.0025, "n2": 0.00313}, "middle": {"p": 0.0025, "n1": 0.0025, "n2": 0.0025}}, "l_2": {"column": {"p": 0.0025, "n1": 0.00291, "n2": 0.00291}, "middle": {"p": 0.0025, "n1": 0.0025, "n2": 0.0025}}}, "E_c": 5144190.898479565, "lambda_cw": 1.0, "n": 5.637426870875134, "f_r": 318.1980515339464, "strips": {"l_1": {"column": 17.0, "middle": 17.0}, "l_2": {"column": 17.0, "middle": 17.0}}, "mass": 8023.7888198757755, "weight": 258.366, "rho_max": 0.021250000000000005, "bending_moments": {"l_1": {"service": {"column": {"n1": {"dl": 230.5, "ll": 86.8}, "n2": {"dl": 465.5, "ll": 175.2}, "p": {"dl": 276.6, "ll": 104.1}}, "middle": {"n1": {"dl": 0.0, "ll": 0.0}, "n2": {"dl": 155.2, "ll": 58.4}, "p": {"dl": 184.4, "ll": 69.4}}}, "factored": {"column": {"n1": 415.5, "n2": 838.9, "p": 498.5}, "middle": {"n1": 0.0, "n2": 279.7, "p": 332.3}}}, "l_2": {"service": {"column": {"n1": {"dl": 432.3, "ll": 162.7}, "n2": {"dl": 432.3, "ll": 162.7}, "p": {"dl": 186.2, "ll": 70.1}}, "middle": {"n1": {"dl": 144.1, "ll": 54.2}, "n2": {"dl": 144.1, "ll": 54.2}, "p": {"dl": 124.1, "ll": 46.7}}}, "factored": {"column": {"n1": 779.1, "n2": 779.1, "p": 335.6}, "middle": {"n1": 259.6, "n2": 259.6, "p": 223.6}}}}, "I_e": 99670.0, "I_g": 167042.0, "k_1": 0.5966762850061661, "f_i": 8.1608464112141, "vib": {"beta": 0.03, "very_slow": {"V_13": 897.0, "crit": "pass"}, "slow": {"V_13": 1426.0, "crit": "pass"}, "moderate": {"V_13": 2868.0, "crit": "pass"}, "fast": {"V_13": 4019.0, "crit": "pass"}}}, {"l_1": 34, "l_2": 34, "h": 18, "f_c": 5000, "c_1": 24, "c_2": 24, "bay": {"l_1": "exterior", "l_2": "interior"}, "l_ratio": 1.0, "f_y": 60000, "w_c": 150, "nu": 0.2, "loading": {"sdl": 0, "ll_design": 80, "ll_vib": 11}, "reinforcement": {"type": "estimated"}, "phi": 0.9, "rho": {"l_1": {"column": {"p": 0.0025, "n1": 0.0025, "n2": 0.003}, "middle": {"p": 0.0025, "n1": 0.0025, "n2": 0.0025}}, "l_2": {"column": {"p": 0.0025, "n1": 0.00279, "n2": 0.00279}, "middle": {"p": 0.0025, "n1": 0.0025, "n2": 0.0025}}}, "E_c": 5144190.898479565, "lambda_cw": 1.0, "n": 5.637426870875134, "f_r": 318.1980515339464, "strips": {"l_1": {"column": 17.0, "middle": 17.0}, "l_2": {"column": 17.0, "middle": 17.0}}, "mass": 8472.546583850932, "weight": 272.816, "rho_max": 0.021250000000000005, "bending_moments": {"l_1": {"service": {"column": {"n1": {"dl": 254.6, "ll": 90.5}, "n2": {"dl": 514.1, "ll": 182.8}, "p": {"dl": 305.5, "ll": 108.6}}, "middle": {"n1": {"dl": 0.0, "ll": 0.0}, "n2": {"dl": 171.4, "ll": 60.9}, "p": {"dl": 203.7, "ll": 72.4}}}, "factored": {"column": {"n1": 450.3, "n2": 909.4, "p": 540.4}, "middle": {"n1": 0.0, "n2": 303.1, "p": 360.3}}}, "l_2": {"service": {"column": {"n1": {"dl": 477.4, "ll": 169.7}, "n2": {"dl": 477.4, "ll": 169.7}, "p": {"dl": 205.6, "ll": 73.1}}, "middle": {"n1": {"dl": 159.1, "ll": 56.6}, "n2": {"dl": 159.1, "ll": 56.6}, "p": {"dl": 137.1, "ll": 48.7}}}, "factored": {"column": {"n1": 844.4, "n2": 844.4, "p": 363.7}, "middle": {"n1": 281.5, "n2": 281.5, "p": 242.4}}}}, "I_e": 119514.69999999998, "I_g": 198288.0, "k_1": 0.6027328935689501, "f_i": 7.868296311162589, "vib": {"beta": 0.03, "very_slow": {"V_13": 890.0, "crit": "pass"}, "slow": {"V_13": 1605.0, "crit": "pass"}, "moderate": {"V_13": 3113.0, "crit": "pass"}, "fast": {"V_13": 4061.0, "crit": "pass"}}}, {"l_1": 34, "l_2": 34, "h": 18, "f_c": 5000, "c_1": 26, "c_2": 26, "bay": {"l_1": "exterior", "l_2": "interior"}, "l_ratio": 1.0, "f_y": 60000, "w_c": 150, "nu": 0.2, "loading": {"sdl": 0, "ll_design": 80, "ll_vib": 11}, "reinforcement": {"type": "estimated"}, "phi": 0.9, "rho": {"l_1": {"column": {"p": 0.0025, "n1": 0.0025, "n2": 0.00297}, "middle": {"p": 0.0025, "n1": 0.0025, "n2": 0.0025}}, "l_2": {"column": {"p": 0.0025, "n1": 0.00276, "n2": 0.00276}, "middle": {"p": 0.0025, "n1": 0.0025, "n2": 0.0025}}}, "E_c": 5144190.898479565, "lambda_cw": 1.0, "n": 5.637426870875134, "f_r": 318.1980515339464, "strips": {"l_1": {"column": 17.0, "middle": 17.0}, "l_2": {"column": 17.0, "middle": 17.0}}, "mass": 8472.546583850932, "weight": 272.816, "rho_max": 0.021250000000000005, "bending_moments": {"l_1": {"service": {"column": {"n1": {"dl": 251.9, "ll": 89.6}, "n2": {"dl": 508.7, "ll": 180.9}, "p": {"dl": 302.3, "ll": 107.5}}, "middle": {"n1": {"dl": 0.0, "ll": 0.0}, "n2": {"dl": 169.6, "ll": 60.3}, "p": {"dl": 201.6, "ll": 71.7}}}, "factored": {"column": {"n1": 445.6, "n2": 899.9, "p": 534.8}, "middle": {"n1": 0.0, "n2": 300.0, "p": 356.6}}}, "l_2": {"service": {"column": {"n1": {"dl": 472.4, "ll": 168.0}, "n2": {"dl": 472.4, "ll": 168.0}, "p": {"dl": 203.5, "ll": 72.4}}, "middle": {"n1": {"dl": 157.5, "ll": 56.0}, "n2": {"dl": 157.5, "ll": 56.0}, "p": {"dl": 135.7, "ll": 48.2}}}, "factored": {"column": {"n1": 835.7, "n2": 835.7, "p": 360.0}, "middle": {"n1": 278.6, "n2": 278.6, "p": 240.0}}}}, "I_e": 119909.39999999998, "I_g": 198288.0, "k_1": 0.6047234325829096, "f_i": 8.710886448166871, "vib": {"beta": 0.03, "very_slow": {"V_13": 781.0, "crit": "pass"}, "slow": {"V_13": 1248.0, "crit": "pass"}, "moderate": {"V_13": 1963.0, "crit": "pass"}, "fast": {"V_13": 3189.0, "crit": "pass"}}}, {"l_1": 34, "l_2": 34, "h": 18, "f_c": 5000, "c_1": 28, "c_2": 28, "bay": {"l_1": "exterior", "l_2": "interior"}, "l_ratio": 1.0, "f_y": 60000, "w_c": 150, "nu": 0.2, "loading": {"sdl": 0, "ll_design": 80, "ll_vib": 11}, "reinforcement": {"type": "estimated"}, "phi": 0.9, "rho": {"l_1": {"column": {"p": 0.0025, "n1": 0.0025, "n2": 0.00294}, "middle": {"p": 0.0025, "n1": 0.0025, "n2": 0.0025}}, "l_2": {"column": {"p": 0.0025, "n1": 0.00273, "n2": 0.00273}, "middle": {"p": 0.0025, "n1": 0.0025, "n2": 0.0025}}}, "E_c": 5144190.898479565, "lambda_cw": 1.0, "n": 5.637426870875134, "f_r": 318.1980515339464, "strips": {"l_1": {"column": 17.0, "middle": 17.0}, "l_2": {"column": 17.0, "middle": 17.0}}, "mass": 8472.546583850932, "weight": 272.816, "rho_max": 0.021250000000000005, "bending_moments": {"l_1": {"service": {"column": {"n1": {"dl": 249.3, "ll": 88.6}, "n2": {"dl": 503.4, "ll": 179.0}, "p": {"dl": 299.2, "ll": 106.4}}, "middle": {"n1": {"dl": 0.0, "ll": 0.0}, "n2": {"dl": 167.8, "ll": 59.7}, "p": {"dl": 199.5, "ll": 70.9}}}, "factored": {"column": {"n1": 440.9, "n2": 890.5, "p": 529.3}, "middle": {"n1": 0.0, "n2": 296.9, "p": 352.8}}}, "l_2": {"service": {"column": {"n1": {"dl": 467.5, "ll": 166.2}, "n2": {"dl": 467.5, "ll": 166.2}, "p": {"dl": 201.4, "ll": 71.6}}, "middle": {"n1": {"dl": 155.8, "ll": 55.4}, "n2": {"dl": 155.8, "ll": 55.4}, "p": {"dl": 134.2, "ll": 47.7}}}, "factored": {"column": {"n1": 826.9, "n2": 826.9, "p": 356.2}, "middle": {"n1": 275.6, "n2": 275.6, "p": 237.4}}}}, "I_e": 120334.84999999998, "I_g": 198288.0, "k_1": 0.6068690490599531, "f_i": 8.726326293193866, "vib": {"beta": 0.03, "very_slow": {"V_13": 778.0, "crit": "pass"}, "slow": {"V_13": 1245.0, "crit": "pass"}, "moderate": {"V_13": 1936.0, "crit": "pass"}, "fast": {"V_13": 3166.0, "crit": "pass"}}}, {"l_1": 34, "l_2": 34, "h": 18, "f_c": 5000, "c_1": 30, "c_2": 30, "bay": {"l_1": "exterior", "l_2": "interior"}, "l_ratio": 1.0, "f_y": 60000, "w_c": 150, "nu": 0.2, "loading": {"sdl": 0, "ll_design": 80, "ll_vib": 11}, "reinforcement": {"type": "estimated"}, "phi": 0.9, "rho": {"l_1": {"column": {"p": 0.0025, "n1": 0.0025, "n2": 0.00291}, "middle": {"p": 0.0025, "n1": 0.0025, "n2": 0.0025}}, "l_2": {"column": {"p": 0.0025, "n1": 0.0027, "n2": 0.0027}, "middle": {"p": 0.0025, "n1": 0.0025, "n2": 0.0025}}}, "E_c": 5144190.898479565, "lambda_cw": 1.0, "n": 5.637426870875134, "f_r": 318.1980515339464, "strips": {"l_1": {"column": 17.0, "middle": 17.0}, "l_2": {"column": 17.0, "middle": 17.0}}, "mass": 8472.546583850932, "weight": 272.816, "rho_max": 0.021250000000000005, "bending_moments": {"l_1": {"service": {"column": {"n1": {"dl": 246.7, "ll": 87.7}, "n2": {"dl": 498.1, "ll": 177.1}, "p": {"dl": 296.0, "ll": 105.3}}, "middle": {"n1": {"dl": 0.0, "ll": 0.0}, "n2": {"dl": 166.0, "ll": 59.0}, "p": {"dl": 197.4, "ll": 70.2}}}, "factored": {"column": {"n1": 436.4, "n2": 881.1, "p": 523.7}, "middle": {"n1": 0.0, "n2": 293.6, "p": 349.2}}}, "l_2": {"service": {"column": {"n1": {"dl": 462.6, "ll": 164.5}, "n2": {"dl": 462.6, "ll": 164.5}, "p": {"dl": 199.3, "ll": 70.8}}, "middle": {"n1": {"dl": 154.2, "ll": 54.8}, "n2": {"dl": 154.2, "ll": 54.8}, "p": {"dl": 132.8, "ll": 47.2}}}, "factored": {"column": {"n1": 818.3, "n2": 818.3, "p": 352.4}, "middle": {"n1": 272.7, "n2": 272.7, "p": 234.9}}}}, "I_e": 120802.79999999999, "I_g": 198288.0, "k_1": 0.609229000242072, "f_i": 8.743277002796532, "vib": {"beta": 0.03, "very_slow": {"V_13": 777.0, "crit": "pass"}, "slow": {"V_13": 1243.0, "crit": "pass"}, "moderate": {"V_13": 1922.0, "crit": "pass"}, "fast": {"V_13": 3155.0, "crit": "pass"}}}, {"l_1": 34, "l_2": 34, "h": 18, "f_c": 5000, "c_1": 32, "c_2": 32, "bay": {"l_1": "exterior", "l_2": "interior"}, "l_ratio": 1.0, "f_y": 60000, "w_c": 150, "nu": 0.2, "loading": {"sdl": 0, "ll_design": 80, "ll_vib": 11}, "reinforcement": {"type": "estimated"}, "phi": 0.9, "rho": {"l_1": {"column": {"p": 0.0025, "n1": 0.0025, "n2": 0.00288}, "middle": {"p": 0.0025, "n1": 0.0025, "n2": 0.0025}}, "l_2": {"column": {"p": 0.0025, "n1": 0.00267, "n2": 0.00267}, "middle": {"p": 0.0025, "n1": 0.0025, "n2": 0.0025}}}, "E_c": 5144190.898479565, "lambda_cw": 1.0, "n": 5.637426870875134, "f_r": 318.1980515339464, "strips": {"l_1": {"column": 17.0, "middle": 17.0}, "l_2": {"column": 17.0, "middle": 17.0}}, "mass": 8472.546583850932, "weight": 272.816, "rho_max": 0.021250000000000005, "bending_moments": {"l_1": {"service": {"column": {"n1": {"dl": 244.1, "ll": 86.8}, "n2": {"dl": 492.9, "ll": 175.2}, "p": {"dl": 292.9, "ll": 104.1}}, "middle": {"n1": {"dl": 0.0, "ll": 0.0}, "n2": {"dl": 164.3, "ll": 58.4}, "p": {"dl": 195.3, "ll": 69.4}}}, "factored": {"column": {"n1": 431.8, "n2": 871.8, "p": 518.0}, "middle": {"n1": 0.0, "n2": 290.6, "p": 345.4}}}, "l_2": {"service": {"column": {"n1": {"dl": 457.7, "ll": 162.7}, "n2": {"dl": 457.7, "ll": 162.7}, "p": {"dl": 197.2, "ll": 70.1}}, "middle": {"n1": {"dl": 152.6, "ll": 54.2}, "n2": {"dl": 152.6, "ll": 54.2}, "p": {"dl": 131.4, "ll": 46.7}}}, "factored": {"column": {"n1": 809.6, "n2": 809.6, "p": 348.8}, "middle": {"n1": 269.8, "n2": 269.8, "p": 232.4}}}}, "I_e": 121316.09999999998, "I_g": 198288.0, "k_1": 0.6118176591624302, "f_i": 8.761832726700057, "vib": {"beta": 0.03, "very_slow": {"V_13": 775.0, "crit": "pass"}, "slow": {"V_13": 1239.0, "crit": "pass"}, "moderate": {"V_13": 1895.0, "crit": "pass"}, "fast": {"V_13": 3133.0, "crit": "pass"}}}]